{
 "generatedAt": "2026-07-20T16:13:39+00:00",
 "generatedAtMs": 1784564001826,
 "window": "month",
 "topN": 20,
 "minAccount": 10000000,
 "focus": [
  "BTC",
  "ETH",
  "ATOM",
  "TAO",
  "XRP",
  "SOL",
  "BNB",
  "DOGE",
  "AVAX"
 ],
 "traders": [
  {
   "addr": "0xd47587702a91731dc1089b5db0932cf820151a91",
   "name": null,
   "accountValue": 50414937.299623996,
   "monthPnl": 14635187.824826,
   "monthRoi": 0.2165876538,
   "positions": [
    {
     "coin": "BTC",
     "side": "long",
     "szi": 1.07572,
     "entryPx": 73399.9,
     "notionalUsd": 70502.6888,
     "leverage": "20x cross",
     "liqPx": null,
     "uPnl": -8455.150196,
     "entryTime": null,
     "entrySince": null
    },
    {
     "coin": "SOL",
     "side": "long",
     "szi": 0.05,
     "entryPx": 86.2438,
     "notionalUsd": 3.88825,
     "leverage": "20x cross",
     "liqPx": null,
     "uPnl": -0.423941,
     "entryTime": null,
     "entrySince": null
    }
   ],
   "rankPnl": 1,
   "rankRoi": 17,
   "changes": {
    "h1": {},
    "h4": {}
   }
  },
  {
   "addr": "0x4e23288cee4960f9f962195c22948e4bc7ae20c3",
   "name": null,
   "accountValue": 29130243.163119,
   "monthPnl": 13191070.487721,
   "monthRoi": 1.0788102927,
   "positions": [
    {
     "coin": "BTC",
     "side": "long",
     "szi": 0.008,
     "entryPx": 61129.3,
     "notionalUsd": 524.32,
     "leverage": "9x cross",
     "liqPx": null,
     "uPnl": 35.285595,
     "entryTime": null,
     "entrySince": null
    },
    {
     "coin": "SOL",
     "side": "long",
     "szi": 12.71,
     "entryPx": 82.02,
     "notionalUsd": 988.39315,
     "leverage": "20x cross",
     "liqPx": null,
     "uPnl": -54.081196,
     "entryTime": null,
     "entrySince": null
    }
   ],
   "rankPnl": 2,
   "rankRoi": 1,
   "changes": {
    "h1": {},
    "h4": {}
   }
  },
  {
   "addr": "0xb83de012dba672c76a7dbbbf3e459cb59d7d6e36",
   "name": null,
   "accountValue": 108550906.486531,
   "monthPnl": 8273695.630604,
   "monthRoi": 0.196030752,
   "positions": [
    {
     "coin": "BTC",
     "side": "short",
     "szi": 818.07501,
     "entryPx": 63798.6,
     "notionalUsd": 53616636.1554,
     "leverage": "5x cross",
     "liqPx": 107866.0296568836,
     "uPnl": -1424534.509053,
     "entryTime": null,
     "entrySince": 1784489188178
    },
    {
     "coin": "ETH",
     "side": "short",
     "szi": 42349.3127,
     "entryPx": 1842.88,
     "notionalUsd": 80556862.61794,
     "leverage": "5x cross",
     "liqPx": 2709.2649082072,
     "uPnl": -2511848.23029,
     "entryTime": null,
     "entrySince": 1784489125434
    },
    {
     "coin": "SOL",
     "side": "short",
     "szi": 197160.37,
     "entryPx": 80.0129,
     "notionalUsd": 15332176.17305,
     "leverage": "5x cross",
     "liqPx": 251.2461131793,
     "uPnl": 443202.35869,
     "entryTime": null,
     "entrySince": null
    },
    {
     "coin": "AVAX",
     "side": "short",
     "szi": 0.41,
     "entryPx": 6.5726,
     "notionalUsd": 2.705221,
     "leverage": "10x cross",
     "liqPx": 79952756.79486252,
     "uPnl": -0.010455,
     "entryTime": null,
     "entrySince": null
    },
    {
     "coin": "DOGE",
     "side": "short",
     "szi": 1.0,
     "entryPx": 0.107181,
     "notionalUsd": 0.073506,
     "leverage": "10x cross",
     "liqPx": 32780627.77380182,
     "uPnl": 0.033675,
     "entryTime": null,
     "entrySince": null
    },
    {
     "coin": "XRP",
     "side": "long",
     "szi": 11459.0,
     "entryPx": 1.394549,
     "notionalUsd": 12765.326,
     "leverage": "5x cross",
     "liqPx": null,
     "uPnl": -3214.8136,
     "entryTime": null,
     "entrySince": null
    }
   ],
   "rankPnl": 3,
   "rankRoi": 18,
   "changes": {
    "h1": {},
    "h4": {}
   }
  },
  {
   "addr": "0xfe7ce058edc7cfcde9ef8262ba51f8d4796ab7ae",
   "name": null,
   "accountValue": 14228679.070069,
   "monthPnl": 7017258.337291,
   "monthRoi": 0.3773026624,
   "positions": [
    {
     "coin": "ETH",
     "side": "short",
     "szi": 138.0486,
     "entryPx": 1792.82,
     "notionalUsd": 262596.04692,
     "leverage": "20x cross",
     "liqPx": 32958.6297687774,
     "uPnl": -15098.60397,
     "entryTime": null,
     "entrySince": null
    }
   ],
   "rankPnl": 4,
   "rankRoi": 9,
   "changes": {
    "h1": {},
    "h4": {}
   }
  },
  {
   "addr": "0xa5b0edf6b55128e0ddae8e51ac538c3188401d41",
   "name": null,
   "accountValue": 33464837.311962,
   "monthPnl": 6671836.159637,
   "monthRoi": 0.2490141407,
   "positions": [
    {
     "coin": "ETH",
     "side": "long",
     "szi": 40000.5788,
     "entryPx": 2265.48,
     "notionalUsd": 76089100.99336,
     "leverage": "15x cross",
     "liqPx": 1068.2805648527,
     "uPnl": -14531806.59283,
     "entryTime": 1764552282115,
     "entrySince": null
    }
   ],
   "rankPnl": 5,
   "rankRoi": 15,
   "changes": {
    "h1": {},
    "h4": {}
   }
  },
  {
   "addr": "0x6c8512516ce5669d35113a11ca8b8de322fd84f6",
   "name": null,
   "accountValue": 32490568.529798,
   "monthPnl": 6119819.814509,
   "monthRoi": 0.2320684892,
   "positions": [
    {
     "coin": "ETH",
     "side": "long",
     "szi": 40000.0,
     "entryPx": 2265.44,
     "notionalUsd": 76088000.0,
     "leverage": "20x cross",
     "liqPx": 1073.9621604643,
     "uPnl": -14529764.973209,
     "entryTime": 1776617838052,
     "entrySince": null
    }
   ],
   "rankPnl": 6,
   "rankRoi": 16,
   "changes": {
    "h1": {},
    "h4": {}
   }
  },
  {
   "addr": "0x7fba7e745bd97f828c824589680749b55a8c04ab",
   "name": null,
   "accountValue": 11355370.59151,
   "monthPnl": 5109695.20151,
   "monthRoi": 0.8181173184,
   "positions": [
    {
     "coin": "ETH",
     "side": "long",
     "szi": 29029.8386,
     "entryPx": 1816.12,
     "notionalUsd": 55220558.98492,
     "leverage": "10x cross",
     "liqPx": 1523.5528069654,
     "uPnl": 2498712.746898,
     "entryTime": 1783354073233,
     "entrySince": null
    }
   ],
   "rankPnl": 7,
   "rankRoi": 2,
   "changes": {
    "h1": {},
    "h4": {}
   }
  },
  {
   "addr": "0xa312114b5795dff9b8db50474dd57701aa78ad1e",
   "name": "NAKED SHORTS ONLY",
   "accountValue": 21733484.399646,
   "monthPnl": 4808798.468137,
   "monthRoi": 0.4508745214,
   "positions": [
    {
     "coin": "BTC",
     "side": "short",
     "szi": 47.36462,
     "entryPx": 61805.1,
     "notionalUsd": 3104277.1948,
     "leverage": "40x cross",
     "liqPx": 198680.1652350282,
     "uPnl": -176900.83959,
     "entryTime": null,
     "entrySince": null
    },
    {
     "coin": "ETH",
     "side": "short",
     "szi": 1029.1423,
     "entryPx": 1763.17,
     "notionalUsd": 1957634.48306,
     "leverage": "20x cross",
     "liqPx": 7984.7064771363,
     "uPnl": -143077.88075,
     "entryTime": null,
     "entrySince": null
    }
   ],
   "rankPnl": 8,
   "rankRoi": 6,
   "changes": {
    "h1": {},
    "h4": {}
   }
  },
  {
   "addr": "0xa875890465da20062bcf3b024bf7d54e69c725a8",
   "name": null,
   "accountValue": 21527679.508443,
   "monthPnl": 4793164.364499,
   "monthRoi": 0.5843781637,
   "positions": [
    {
     "coin": "ETH",
     "side": "long",
     "szi": 30000.0,
     "entryPx": 2243.12,
     "notionalUsd": 57066000.0,
     "leverage": "20x cross",
     "liqPx": 1183.8106772213,
     "uPnl": -10227744.23629,
     "entryTime": 1776928588935,
     "entrySince": null
    }
   ],
   "rankPnl": 9,
   "rankRoi": 3,
   "changes": {
    "h1": {},
    "h4": {}
   }
  },
  {
   "addr": "0x5b5d51203a0f9079f8aeb098a6523a13f298c060",
   "name": null,
   "accountValue": 48554108.460988,
   "monthPnl": 3874930.008218,
   "monthRoi": 0.3069550241,
   "positions": [
    {
     "coin": "BTC",
     "side": "short",
     "szi": 411.2877,
     "entryPx": 63728.7,
     "notionalUsd": 26955795.858,
     "leverage": "10x cross",
     "liqPx": 105493.0248860186,
     "uPnl": -744942.25674,
     "entryTime": null,
     "entrySince": 1784284640467
    },
    {
     "coin": "ETH",
     "side": "short",
     "szi": 21273.3014,
     "entryPx": 1849.15,
     "notionalUsd": 40466073.92308,
     "leverage": "10x cross",
     "liqPx": 2668.9527713284,
     "uPnl": -1128535.615655,
     "entryTime": null,
     "entrySince": 1784286858407
    },
    {
     "coin": "SOL",
     "side": "short",
     "szi": 102082.34,
     "entryPx": 80.4327,
     "notionalUsd": 7938433.1701,
     "leverage": "10x cross",
     "liqPx": 236.7718877763,
     "uPnl": 272327.299479,
     "entryTime": null,
     "entrySince": null
    },
    {
     "coin": "XRP",
     "side": "short",
     "szi": 249233.0,
     "entryPx": 1.901026,
     "notionalUsd": 277645.562,
     "leverage": "20x cross",
     "liqPx": 66.2409903276,
     "uPnl": 196152.933682,
     "entryTime": null,
     "entrySince": null
    }
   ],
   "rankPnl": 10,
   "rankRoi": 10,
   "changes": {
    "h1": {},
    "h4": {}
   }
  },
  {
   "addr": "0x45d26f28196d226497130c4bac709d808fed4029",
   "name": null,
   "accountValue": 34267201.82391,
   "monthPnl": 3129721.361211,
   "monthRoi": 0.2510297451,
   "positions": [
    {
     "coin": "BTC",
     "side": "short",
     "szi": 229.8,
     "entryPx": 80262.5,
     "notionalUsd": 15061092.0,
     "leverage": "20x cross",
     "liqPx": 146130.9147072903,
     "uPnl": 3383248.009051,
     "entryTime": null,
     "entrySince": null
    },
    {
     "coin": "ETH",
     "side": "short",
     "szi": 5037.0,
     "entryPx": 2385.27,
     "notionalUsd": 9581381.4,
     "leverage": "20x cross",
     "liqPx": 5551.9155563014,
     "uPnl": 2433255.245793,
     "entryTime": null,
     "entrySince": 1778344214504
    },
    {
     "coin": "ATOM",
     "side": "short",
     "szi": 24600.0,
     "entryPx": 10.1735,
     "notionalUsd": 36749.94,
     "leverage": "5x cross",
     "liqPx": 745.1500412743,
     "uPnl": 213518.62346,
     "entryTime": null,
     "entrySince": null
    },
    {
     "coin": "SOL",
     "side": "short",
     "szi": 25120.0,
     "entryPx": 93.5333,
     "notionalUsd": 1953456.8,
     "leverage": "20x cross",
     "liqPx": 806.0269854836,
     "uPnl": 396100.07738,
     "entryTime": null,
     "entrySince": 1778344213403
    },
    {
     "coin": "AVAX",
     "side": "short",
     "szi": 9870.0,
     "entryPx": 49.454,
     "notionalUsd": 65123.247,
     "leverage": "10x cross",
     "liqPx": 1860.0875706533,
     "uPnl": 422988.14519,
     "entryTime": null,
     "entrySince": null
    },
    {
     "coin": "BNB",
     "side": "short",
     "szi": 128.0,
     "entryPx": 697.335,
     "notionalUsd": 73555.2,
     "leverage": "10x cross",
     "liqPx": 134790.6431976704,
     "uPnl": 15703.71437,
     "entryTime": null,
     "entrySince": null
    },
    {
     "coin": "DOGE",
     "side": "short",
     "szi": 6786000.0,
     "entryPx": 0.107053,
     "notionalUsd": 498811.716,
     "leverage": "10x cross",
     "liqPx": 2.7051551379,
     "uPnl": 227654.68821,
     "entryTime": null,
     "entrySince": null
    },
    {
     "coin": "XRP",
     "side": "short",
     "szi": 149000.0,
     "entryPx": 1.419711,
     "notionalUsd": 165986.0,
     "leverage": "20x cross",
     "liqPx": 123.8921280225,
     "uPnl": 45551.0337,
     "entryTime": null,
     "entrySince": 1778424878315
    },
    {
     "coin": "TAO",
     "side": "short",
     "szi": 1890.0,
     "entryPx": 321.714,
     "notionalUsd": 370666.8,
     "leverage": "5x cross",
     "liqPx": 9215.4993180529,
     "uPnl": 237374.39139,
     "entryTime": 1778425477313,
     "entrySince": null
    }
   ],
   "rankPnl": 11,
   "rankRoi": 13,
   "changes": {
    "h1": {},
    "h4": {}
   }
  },
  {
   "addr": "0xf822fa0fd364c573fcdb7009fcf47601bc8be01a",
   "name": null,
   "accountValue": 60132685.177788,
   "monthPnl": 2997290.386563,
   "monthRoi": 0.0524594325,
   "positions": [
    {
     "coin": "BTC",
     "side": "short",
     "szi": 853.45419,
     "entryPx": 62236.7,
     "notionalUsd": 55935387.6126,
     "leverage": "3x cross",
     "liqPx": 125481.1497892573,
     "uPnl": -2819194.391934,
     "entryTime": null,
     "entrySince": 1783518773306
    },
    {
     "coin": "ETH",
     "side": "short",
     "szi": 18257.3869,
     "entryPx": 1734.56,
     "notionalUsd": 34729201.36118,
     "leverage": "3x cross",
     "liqPx": 4683.5876717608,
     "uPnl": -3060557.221628,
     "entryTime": null,
     "entrySince": 1783518918696
    },
    {
     "coin": "SOL",
     "side": "short",
     "szi": 141406.03,
     "entryPx": 76.4987,
     "notionalUsd": 10996439.92295,
     "leverage": "3x cross",
     "liqPx": 435.1271243531,
     "uPnl": -179051.003528,
     "entryTime": null,
     "entrySince": 1783519260261
    }
   ],
   "rankPnl": 12,
   "rankRoi": 29,
   "changes": {
    "h1": {},
    "h4": {}
   }
  },
  {
   "addr": "0xfc667adba8d4837586078f4fdcdc29804337ca06",
   "name": null,
   "accountValue": 95231618.37983099,
   "monthPnl": 2943992.89719,
   "monthRoi": 0.0352338533,
   "positions": [
    {
     "coin": "BTC",
     "side": "short",
     "szi": 117.47818,
     "entryPx": 64132.2,
     "notionalUsd": 7699519.9172,
     "leverage": "20x cross",
     "liqPx": 227553.6951167075,
     "uPnl": -165377.09755,
     "entryTime": null,
     "entrySince": 1784515692083
    },
    {
     "coin": "ETH",
     "side": "short",
     "szi": 10107.3245,
     "entryPx": 1802.74,
     "notionalUsd": 19226152.6639,
     "leverage": "20x cross",
     "liqPx": 3771.4508550192,
     "uPnl": -1005234.670289,
     "entryTime": null,
     "entrySince": 1784517816343
    },
    {
     "coin": "SOL",
     "side": "short",
     "szi": 94695.37,
     "entryPx": 77.6205,
     "notionalUsd": 7363985.44805,
     "leverage": "20x cross",
     "liqPx": 276.3065271981,
     "uPnl": -13676.047285,
     "entryTime": null,
     "entrySince": 1784515851643
    },
    {
     "coin": "XRP",
     "side": "short",
     "szi": 4335362.0,
     "entryPx": 1.098023,
     "notionalUsd": 4829593.268,
     "leverage": "20x cross",
     "liqPx": 5.4506536355,
     "uPnl": -69261.891112,
     "entryTime": null,
     "entrySince": 1784517766548
    }
   ],
   "rankPnl": 13,
   "rankRoi": 31,
   "changes": {
    "h1": {},
    "h4": {}
   }
  },
  {
   "addr": "0x469e9a7f624b04c24f0e64edf8d8a277e6bf58a5",
   "name": null,
   "accountValue": 16651060.165461,
   "monthPnl": 2650876.463465,
   "monthRoi": 0.4500653481,
   "positions": [
    {
     "coin": "BTC",
     "side": "long",
     "szi": 313.37378,
     "entryPx": 64289.7,
     "notionalUsd": 20538517.5412,
     "leverage": "25x cross",
     "liqPx": 46080.1770021826,
     "uPnl": 391794.379125,
     "entryTime": 1781473010238,
     "entrySince": null
    },
    {
     "coin": "ETH",
     "side": "long",
     "szi": 15606.9664,
     "entryPx": 1899.3,
     "notionalUsd": 29687571.48608,
     "leverage": "25x cross",
     "liqPx": 1508.4740177466,
     "uPnl": 45141.04316,
     "entryTime": null,
     "entrySince": null
    },
    {
     "coin": "XRP",
     "side": "short",
     "szi": 10500100.0,
     "entryPx": 1.069595,
     "notionalUsd": 11697111.4,
     "leverage": "20x cross",
     "liqPx": 1.6735273831,
     "uPnl": -466252.6575,
     "entryTime": null,
     "entrySince": 1781470770625
    }
   ],
   "rankPnl": 14,
   "rankRoi": 7,
   "changes": {
    "h1": {},
    "h4": {}
   }
  },
  {
   "addr": "0x939f95036d2e7b6d7419ec072bf9d967352204d2",
   "name": null,
   "accountValue": 18132476.021063,
   "monthPnl": 2441744.97467,
   "monthRoi": 0.4320028697,
   "positions": [
    {
     "coin": "BTC",
     "side": "long",
     "szi": 68.22814,
     "entryPx": 70588.0,
     "notionalUsd": 4471672.2956,
     "leverage": "40x cross",
     "liqPx": 16791.3223104467,
     "uPnl": -344417.442233,
     "entryTime": 1760122104686,
     "entrySince": null
    }
   ],
   "rankPnl": 15,
   "rankRoi": 8,
   "changes": {
    "h1": {},
    "h4": {}
   }
  },
  {
   "addr": "0x77375a8c9d13bf79afb2a87f1b0ac1dfd5f5bf66",
   "name": null,
   "accountValue": 32825125.050145004,
   "monthPnl": 2204020.731262,
   "monthRoi": 0.5550717445,
   "positions": [
    {
     "coin": "BTC",
     "side": "short",
     "szi": 231.42877,
     "entryPx": 64343.9,
     "notionalUsd": 15167841.5858,
     "leverage": "15x cross",
     "liqPx": 127800.4089199156,
     "uPnl": -276810.820456,
     "entryTime": null,
     "entrySince": 1753257574605
    },
    {
     "coin": "SOL",
     "side": "short",
     "szi": 45971.64,
     "entryPx": 76.3609,
     "notionalUsd": 3574984.5846,
     "leverage": "10x cross",
     "liqPx": 387.3717961653,
     "uPnl": -64546.05649,
     "entryTime": null,
     "entrySince": 1753496225366
    }
   ],
   "rankPnl": 16,
   "rankRoi": 4,
   "changes": {
    "h1": {},
    "h4": {}
   }
  },
  {
   "addr": "0xc26cbb6483229e0d0f9a1cab675271eda535b8f4",
   "name": null,
   "accountValue": 23924205.971137,
   "monthPnl": 2080680.668099,
   "monthRoi": 0.095253886,
   "positions": [
    {
     "coin": "BTC",
     "side": "long",
     "szi": 79.65619,
     "entryPx": 67243.1,
     "notionalUsd": 5220666.6926,
     "leverage": "2x cross",
     "liqPx": null,
     "uPnl": -135667.71386,
     "entryTime": 1774537145982,
     "entrySince": null
    },
    {
     "coin": "SOL",
     "side": "long",
     "szi": 91276.13,
     "entryPx": 131.022,
     "notionalUsd": 7098088.24945,
     "leverage": "2x cross",
     "liqPx": null,
     "uPnl": -4861101.346869,
     "entryTime": null,
     "entrySince": null
    },
    {
     "coin": "XRP",
     "side": "long",
     "szi": 4014025.0,
     "entryPx": 1.324002,
     "notionalUsd": 4471623.85,
     "leverage": "1x cross",
     "liqPx": null,
     "uPnl": -842953.7143,
     "entryTime": null,
     "entrySince": null
    }
   ],
   "rankPnl": 17,
   "rankRoi": 23,
   "changes": {
    "h1": {},
    "h4": {}
   }
  },
  {
   "addr": "0xa98143608a6846453c88f29506d64a8b85532e65",
   "name": null,
   "accountValue": 15940402.590565,
   "monthPnl": 1932425.785993,
   "monthRoi": 0.4995135151,
   "positions": [
    {
     "coin": "ETH",
     "side": "short",
     "szi": 739.0,
     "entryPx": 2046.49,
     "notionalUsd": 1405578.0,
     "leverage": "20x cross",
     "liqPx": 12246.2391700151,
     "uPnl": 106782.144385,
     "entryTime": null,
     "entrySince": 1776581755220
    },
    {
     "coin": "SOL",
     "side": "short",
     "szi": 310.1,
     "entryPx": 89.515,
     "notionalUsd": 24114.9265,
     "leverage": "20x cross",
     "liqPx": 24608.8937517748,
     "uPnl": 3643.675,
     "entryTime": 1773997784790,
     "entrySince": null
    }
   ],
   "rankPnl": 18,
   "rankRoi": 5,
   "changes": {
    "h1": {},
    "h4": {}
   }
  },
  {
   "addr": "0x60a8c761f39696b3b419f31dcda20b405cb685f6",
   "name": null,
   "accountValue": 29683812.230263,
   "monthPnl": 1875878.727676,
   "monthRoi": 0.1048946975,
   "positions": [
    {
     "coin": "BTC",
     "side": "long",
     "szi": 0.021,
     "entryPx": 66618.6,
     "notionalUsd": 1376.151,
     "leverage": "20x cross",
     "liqPx": null,
     "uPnl": -22.84,
     "entryTime": null,
     "entrySince": null
    }
   ],
   "rankPnl": 19,
   "rankRoi": 20,
   "changes": {
    "h1": {},
    "h4": {}
   }
  },
  {
   "addr": "0x960b6c2c4b1498681b8422eb572a8b3a6aa3f0fc",
   "name": null,
   "accountValue": 17740617.551606,
   "monthPnl": 1646382.656916,
   "monthRoi": 0.102173263,
   "positions": [
    {
     "coin": "ETH",
     "side": "short",
     "szi": 1081.4693,
     "entryPx": 1849.2,
     "notionalUsd": 2056954.6086,
     "leverage": "6x cross",
     "liqPx": 8057.7655471226,
     "uPnl": -57100.05426,
     "entryTime": 1758158624526,
     "entrySince": null
    }
   ],
   "rankPnl": 20,
   "rankRoi": 21,
   "changes": {
    "h1": {},
    "h4": {}
   }
  },
  {
   "addr": "0xaf0fdd39e5d92499b0ed9f68693da99c0ec1e92e",
   "name": null,
   "accountValue": 11568339.810177,
   "monthPnl": 1128544.362703,
   "monthRoi": 0.2957355347,
   "positions": [
    {
     "coin": "BTC",
     "side": "short",
     "szi": 78.93688,
     "entryPx": 64742.1,
     "notionalUsd": 5172812.68328,
     "leverage": "30x cross",
     "liqPx": 112694.6100503042,
     "uPnl": -62266.765263,
     "entryTime": 1761058760258,
     "entrySince": null
    }
   ],
   "rankPnl": 26,
   "rankRoi": 11,
   "changes": {
    "h1": {},
    "h4": {}
   }
  },
  {
   "addr": "0xcac19662ec88d23fa1c81ac0e8570b0cf2ff26b3",
   "name": null,
   "accountValue": 21285693.78846,
   "monthPnl": 1167736.076418,
   "monthRoi": 0.2622618291,
   "positions": [
    {
     "coin": "BTC",
     "side": "short",
     "szi": 104.66857,
     "entryPx": 61787.7,
     "notionalUsd": 6859036.06067,
     "leverage": "20x cross",
     "liqPx": 153616.7104675899,
     "uPnl": -391803.14615,
     "entryTime": null,
     "entrySince": null
    },
    {
     "coin": "ETH",
     "side": "short",
     "szi": 1551.8588,
     "entryPx": 1757.92,
     "notionalUsd": 2951635.4376,
     "leverage": "20x cross",
     "liqPx": 7799.4519238894,
     "uPnl": -223582.55943,
     "entryTime": null,
     "entrySince": null
    },
    {
     "coin": "SOL",
     "side": "short",
     "szi": 32296.86,
     "entryPx": 73.747,
     "notionalUsd": 2511565.3179,
     "leverage": "20x cross",
     "liqPx": 359.7542925022,
     "uPnl": -129768.387214,
     "entryTime": null,
     "entrySince": null
    },
    {
     "coin": "AVAX",
     "side": "long",
     "szi": 71886.42,
     "entryPx": 6.4048,
     "notionalUsd": 474234.71274,
     "leverage": "10x cross",
     "liqPx": null,
     "uPnl": 13812.353677,
     "entryTime": null,
     "entrySince": null
    },
    {
     "coin": "BNB",
     "side": "short",
     "szi": 300.0,
     "entryPx": 572.973,
     "notionalUsd": 172386.0,
     "leverage": "10x cross",
     "liqPx": 29291.0855120545,
     "uPnl": -493.86226,
     "entryTime": null,
     "entrySince": null
    },
    {
     "coin": "DOGE",
     "side": "long",
     "szi": 996620.0,
     "entryPx": 0.084106,
     "notionalUsd": 73250.57338,
     "leverage": "10x cross",
     "liqPx": null,
     "uPnl": -10571.91746,
     "entryTime": null,
     "entrySince": null
    },
    {
     "coin": "XRP",
     "side": "long",
     "szi": 704888.0,
     "entryPx": 1.371665,
     "notionalUsd": 785245.232,
     "leverage": "20x cross",
     "liqPx": null,
     "uPnl": -181625.536688,
     "entryTime": null,
     "entrySince": null
    },
    {
     "coin": "TAO",
     "side": "short",
     "szi": 789.82,
     "entryPx": 288.282,
     "notionalUsd": 154899.4984,
     "leverage": "5x cross",
     "liqPx": 10940.8615164537,
     "uPnl": 72792.041232,
     "entryTime": null,
     "entrySince": null
    }
   ],
   "rankPnl": 24,
   "rankRoi": 12,
   "changes": {
    "h1": {},
    "h4": {}
   }
  },
  {
   "addr": "0x3bcae23e8c380dab4732e9a159c0456f12d866f3",
   "name": null,
   "accountValue": 11218524.26949,
   "monthPnl": 613200.17382,
   "monthRoi": 0.2509303148,
   "positions": [
    {
     "coin": "BTC",
     "side": "short",
     "szi": 32.22828,
     "entryPx": 65488.0,
     "notionalUsd": 2111951.41668,
     "leverage": "40x cross",
     "liqPx": 401591.8633674188,
     "uPnl": -1383.994237,
     "entryTime": 1784140821737,
     "entrySince": null
    },
    {
     "coin": "ETH",
     "side": "short",
     "szi": 865.2176,
     "entryPx": 1891.19,
     "notionalUsd": 1645643.8752,
     "leverage": "25x cross",
     "liqPx": 14327.8063743529,
     "uPnl": -9346.173122,
     "entryTime": 1784093329576,
     "entrySince": null
    }
   ],
   "rankPnl": 31,
   "rankRoi": 14,
   "changes": {
    "h1": {},
    "h4": {}
   }
  },
  {
   "addr": "0x8af700ba841f30e0a3fcb0ee4c4a9d223e1efa05",
   "name": null,
   "accountValue": 23543860.246113,
   "monthPnl": 1235950.998431,
   "monthRoi": 0.1355971355,
   "positions": [
    {
     "coin": "BTC",
     "side": "long",
     "szi": 41.13883,
     "entryPx": 70834.4,
     "notionalUsd": 2695868.66873,
     "leverage": "40x cross",
     "liqPx": null,
     "uPnl": -218176.251661,
     "entryTime": null,
     "entrySince": null
    },
    {
     "coin": "ETH",
     "side": "long",
     "szi": 37.4459,
     "entryPx": 1844.48,
     "notionalUsd": 71222.1018,
     "leverage": "25x cross",
     "liqPx": null,
     "uPnl": 2153.822701,
     "entryTime": null,
     "entrySince": null
    },
    {
     "coin": "AVAX",
     "side": "short",
     "szi": 12091.83,
     "entryPx": 42.1163,
     "notionalUsd": 79769.80251,
     "leverage": "10x cross",
     "liqPx": 1605.5631645608,
     "uPnl": 429494.50834,
     "entryTime": null,
     "entrySince": null
    },
    {
     "coin": "XRP",
     "side": "short",
     "szi": 690000.0,
     "entryPx": 1.494361,
     "notionalUsd": 768660.0,
     "leverage": "20x cross",
     "liqPx": 29.1349087502,
     "uPnl": 262449.4156,
     "entryTime": null,
     "entrySince": null
    }
   ],
   "rankPnl": 23,
   "rankRoi": 19,
   "changes": {
    "h1": {},
    "h4": {}
   }
  }
 ],
 "aggregates": [
  {
   "coin": "ETH",
   "long": 6,
   "short": 11,
   "longNotional": 294222453.56616,
   "shortNotional": 194839714.41747996,
   "totalNotional": 489062167.98363996,
   "score": 20
  },
  {
   "coin": "BTC",
   "long": 7,
   "short": 10,
   "longNotional": 32999128.357930005,
   "shortNotional": 191684350.48443,
   "totalNotional": 224683478.84236,
   "score": -71
  },
  {
   "coin": "SOL",
   "long": 3,
   "short": 8,
   "longNotional": 7099080.53085,
   "shortNotional": 49695156.343150005,
   "totalNotional": 56794236.874000005,
   "score": -75
  },
  {
   "coin": "XRP",
   "long": 3,
   "short": 5,
   "longNotional": 5269634.408,
   "shortNotional": 17738996.23,
   "totalNotional": 23008630.638,
   "score": -54
  },
  {
   "coin": "AVAX",
   "long": 1,
   "short": 3,
   "longNotional": 474234.71274,
   "shortNotional": 144895.754731,
   "totalNotional": 619130.467471,
   "score": 53
  },
  {
   "coin": "DOGE",
   "long": 1,
   "short": 2,
   "longNotional": 73250.57338,
   "shortNotional": 498811.789506,
   "totalNotional": 572062.362886,
   "score": -74
  },
  {
   "coin": "TAO",
   "long": 0,
   "short": 2,
   "longNotional": 0.0,
   "shortNotional": 525566.2984,
   "totalNotional": 525566.2984,
   "score": -100
  },
  {
   "coin": "BNB",
   "long": 0,
   "short": 2,
   "longNotional": 0.0,
   "shortNotional": 245941.2,
   "totalNotional": 245941.2,
   "score": -100
  },
  {
   "coin": "ATOM",
   "long": 0,
   "short": 1,
   "longNotional": 0.0,
   "shortNotional": 36749.94,
   "totalNotional": 36749.94,
   "score": -100
  }
 ]
}