{
 "generatedAt": "2026-07-20T04:01:18+00:00",
 "generatedAtMs": 1784520067890,
 "window": "month",
 "topN": 20,
 "minAccount": 10000000,
 "focus": [
  "BTC",
  "ETH",
  "ATOM",
  "TAO",
  "XRP",
  "SOL",
  "BNB",
  "DOGE",
  "AVAX"
 ],
 "traders": [
  {
   "addr": "0xd47587702a91731dc1089b5db0932cf820151a91",
   "name": null,
   "accountValue": 52195996.267225996,
   "monthPnl": 15316236.792428,
   "monthRoi": 0.2266665677,
   "positions": [
    {
     "coin": "BTC",
     "side": "long",
     "szi": 1.46541,
     "entryPx": 73399.9,
     "notionalUsd": 94970.29128,
     "leverage": "20x cross",
     "liqPx": null,
     "uPnl": -12590.79048,
     "entryTime": null,
     "entrySince": null
    },
    {
     "coin": "SOL",
     "side": "long",
     "szi": 0.05,
     "entryPx": 86.2438,
     "notionalUsd": 3.8333,
     "leverage": "20x cross",
     "liqPx": null,
     "uPnl": -0.478891,
     "entryTime": null,
     "entrySince": null
    }
   ],
   "rankPnl": 1,
   "rankRoi": 17,
   "changes": {
    "h1": {},
    "h4": {}
   }
  },
  {
   "addr": "0x4e23288cee4960f9f962195c22948e4bc7ae20c3",
   "name": null,
   "accountValue": 29080754.130005,
   "monthPnl": 13130339.656882,
   "monthRoi": 1.0738435202,
   "positions": [
    {
     "coin": "BTC",
     "side": "long",
     "szi": 0.008,
     "entryPx": 61129.3,
     "notionalUsd": 518.464,
     "leverage": "9x cross",
     "liqPx": null,
     "uPnl": 29.429595,
     "entryTime": null,
     "entrySince": null
    },
    {
     "coin": "SOL",
     "side": "long",
     "szi": 12.71,
     "entryPx": 82.02,
     "notionalUsd": 974.42486,
     "leverage": "20x cross",
     "liqPx": null,
     "uPnl": -68.049486,
     "entryTime": null,
     "entrySince": null
    }
   ],
   "rankPnl": 2,
   "rankRoi": 1,
   "changes": {
    "h1": {},
    "h4": {}
   }
  },
  {
   "addr": "0xb83de012dba672c76a7dbbbf3e459cb59d7d6e36",
   "name": null,
   "accountValue": 107280650.23353,
   "monthPnl": 7294136.091115001,
   "monthRoi": 0.1839027418,
   "positions": [
    {
     "coin": "BTC",
     "side": "short",
     "szi": 817.55932,
     "entryPx": 63798.3,
     "notionalUsd": 52984384.41056,
     "leverage": "5x cross",
     "liqPx": 110790.9300666655,
     "uPnl": -825457.12765,
     "entryTime": null,
     "entrySince": null
    },
    {
     "coin": "ETH",
     "side": "short",
     "szi": 31641.6809,
     "entryPx": 1837.6,
     "notionalUsd": 59448390.07492,
     "leverage": "5x cross",
     "liqPx": 3058.1731298001,
     "uPnl": -1303377.12634,
     "entryTime": null,
     "entrySince": 1784274471055
    },
    {
     "coin": "SOL",
     "side": "short",
     "szi": 197160.37,
     "entryPx": 80.0129,
     "notionalUsd": 15115496.92642,
     "leverage": "5x cross",
     "liqPx": 265.0167947876,
     "uPnl": 659881.60532,
     "entryTime": null,
     "entrySince": null
    },
    {
     "coin": "AVAX",
     "side": "short",
     "szi": 0.41,
     "entryPx": 6.5726,
     "notionalUsd": 2.702843,
     "leverage": "10x cross",
     "liqPx": 86615738.44314191,
     "uPnl": -0.008077,
     "entryTime": null,
     "entrySince": null
    },
    {
     "coin": "DOGE",
     "side": "short",
     "szi": 1.0,
     "entryPx": 0.107181,
     "notionalUsd": 0.072686,
     "leverage": "10x cross",
     "liqPx": 35512450.251083635,
     "uPnl": 0.034495,
     "entryTime": null,
     "entrySince": null
    },
    {
     "coin": "XRP",
     "side": "long",
     "szi": 11459.0,
     "entryPx": 1.394549,
     "notionalUsd": 12596.8787,
     "leverage": "5x cross",
     "liqPx": null,
     "uPnl": -3383.2609,
     "entryTime": null,
     "entrySince": null
    }
   ],
   "rankPnl": 3,
   "rankRoi": 18,
   "changes": {
    "h1": {},
    "h4": {}
   }
  },
  {
   "addr": "0x6c8512516ce5669d35113a11ca8b8de322fd84f6",
   "name": null,
   "accountValue": 33213778.589795,
   "monthPnl": 6843029.874506,
   "monthRoi": 0.2594931964,
   "positions": [
    {
     "coin": "ETH",
     "side": "long",
     "szi": 40000.0,
     "entryPx": 2265.44,
     "notionalUsd": 75152000.0,
     "leverage": "20x cross",
     "liqPx": 1073.6760404389,
     "uPnl": -15465764.973209,
     "entryTime": 1776617838052,
     "entrySince": null
    }
   ],
   "rankPnl": 4,
   "rankRoi": 13,
   "changes": {
    "h1": {},
    "h4": {}
   }
  },
  {
   "addr": "0xfe7ce058edc7cfcde9ef8262ba51f8d4796ab7ae",
   "name": null,
   "accountValue": 17974633.254303,
   "monthPnl": 6768297.909413,
   "monthRoi": 0.3639166037,
   "positions": [
    {
     "coin": "ETH",
     "side": "short",
     "szi": 138.0486,
     "entryPx": 1792.82,
     "notionalUsd": 259365.70968,
     "leverage": "20x cross",
     "liqPx": 35955.7372381829,
     "uPnl": -11868.26673,
     "entryTime": null,
     "entrySince": null
    }
   ],
   "rankPnl": 5,
   "rankRoi": 9,
   "changes": {
    "h1": {},
    "h4": {}
   }
  },
  {
   "addr": "0xa5b0edf6b55128e0ddae8e51ac538c3188401d41",
   "name": null,
   "accountValue": 33304039.495245,
   "monthPnl": 6511038.34292,
   "monthRoi": 0.2430126549,
   "positions": [
    {
     "coin": "ETH",
     "side": "long",
     "szi": 40000.5788,
     "entryPx": 2265.48,
     "notionalUsd": 75153087.44944,
     "leverage": "15x cross",
     "liqPx": 1067.9944448274,
     "uPnl": -15467820.13675,
     "entryTime": 1764552282115,
     "entrySince": null
    }
   ],
   "rankPnl": 6,
   "rankRoi": 15,
   "changes": {
    "h1": {},
    "h4": {}
   }
  },
  {
   "addr": "0x7fba7e745bd97f828c824589680749b55a8c04ab",
   "name": null,
   "accountValue": 11055205.333494,
   "monthPnl": 4809529.943494,
   "monthRoi": 0.7700576228,
   "positions": [
    {
     "coin": "ETH",
     "side": "long",
     "szi": 29029.8386,
     "entryPx": 1816.12,
     "notionalUsd": 54541260.76168,
     "leverage": "10x cross",
     "liqPx": 1523.2666869401,
     "uPnl": 1819414.523658,
     "entryTime": 1783354073233,
     "entrySince": null
    }
   ],
   "rankPnl": 7,
   "rankRoi": 2,
   "changes": {
    "h1": {},
    "h4": {}
   }
  },
  {
   "addr": "0xa875890465da20062bcf3b024bf7d54e69c725a8",
   "name": null,
   "accountValue": 21521082.89094,
   "monthPnl": 4786567.746996,
   "monthRoi": 0.5835739102,
   "positions": [
    {
     "coin": "ETH",
     "side": "long",
     "szi": 30000.0,
     "entryPx": 2243.12,
     "notionalUsd": 56364000.0,
     "leverage": "20x cross",
     "liqPx": 1183.5245571959,
     "uPnl": -10929744.23629,
     "entryTime": 1776928588935,
     "entrySince": null
    }
   ],
   "rankPnl": 8,
   "rankRoi": 3,
   "changes": {
    "h1": {},
    "h4": {}
   }
  },
  {
   "addr": "0xa312114b5795dff9b8db50474dd57701aa78ad1e",
   "name": "NAKED SHORTS ONLY",
   "accountValue": 21540010.941138,
   "monthPnl": 4686591.653212,
   "monthRoi": 0.4394163703,
   "positions": [
    {
     "coin": "BTC",
     "side": "short",
     "szi": 47.36462,
     "entryPx": 61805.1,
     "notionalUsd": 3069606.29296,
     "leverage": "40x cross",
     "liqPx": 206776.5735121633,
     "uPnl": -142229.93775,
     "entryTime": null,
     "entrySince": null
    },
    {
     "coin": "ETH",
     "side": "short",
     "szi": 1029.1423,
     "entryPx": 1763.17,
     "notionalUsd": 1933552.55324,
     "leverage": "20x cross",
     "liqPx": 8364.6321785398,
     "uPnl": -118995.95093,
     "entryTime": null,
     "entrySince": null
    }
   ],
   "rankPnl": 9,
   "rankRoi": 8,
   "changes": {
    "h1": {},
    "h4": {}
   }
  },
  {
   "addr": "0x5b5d51203a0f9079f8aeb098a6523a13f298c060",
   "name": null,
   "accountValue": 48053918.017844,
   "monthPnl": 3492524.820956,
   "monthRoi": 0.2766625561,
   "positions": [
    {
     "coin": "BTC",
     "side": "short",
     "szi": 411.2877,
     "entryPx": 63728.7,
     "notionalUsd": 26654733.2616,
     "leverage": "10x cross",
     "liqPx": 109117.4786766442,
     "uPnl": -443879.66034,
     "entryTime": null,
     "entrySince": 1784284640467
    },
    {
     "coin": "ETH",
     "side": "short",
     "szi": 21273.3014,
     "entryPx": 1849.15,
     "notionalUsd": 39968278.67032,
     "leverage": "10x cross",
     "liqPx": 2729.1590320974,
     "uPnl": -630740.362895,
     "entryTime": null,
     "entrySince": 1784286858407
    },
    {
     "coin": "SOL",
     "side": "short",
     "szi": 102082.34,
     "entryPx": 80.4327,
     "notionalUsd": 7826244.67844,
     "leverage": "10x cross",
     "liqPx": 253.0109031322,
     "uPnl": 384515.791139,
     "entryTime": null,
     "entrySince": null
    },
    {
     "coin": "XRP",
     "side": "short",
     "szi": 249233.0,
     "entryPx": 1.901026,
     "notionalUsd": 273981.8369,
     "leverage": "20x cross",
     "liqPx": 73.3276981608,
     "uPnl": 199816.658782,
     "entryTime": null,
     "entrySince": null
    }
   ],
   "rankPnl": 10,
   "rankRoi": 11,
   "changes": {
    "h1": {},
    "h4": {}
   }
  },
  {
   "addr": "0x469e9a7f624b04c24f0e64edf8d8a277e6bf58a5",
   "name": null,
   "accountValue": 17038417.313193,
   "monthPnl": 3093419.638309,
   "monthRoi": 0.5252002518,
   "positions": [
    {
     "coin": "BTC",
     "side": "long",
     "szi": 313.37378,
     "entryPx": 64289.7,
     "notionalUsd": 20309127.93424,
     "leverage": "25x cross",
     "liqPx": 45261.956482482,
     "uPnl": 162404.772165,
     "entryTime": 1781473010238,
     "entrySince": null
    },
    {
     "coin": "ETH",
     "side": "long",
     "szi": 15606.9664,
     "entryPx": 1899.3,
     "notionalUsd": 29322368.47232,
     "leverage": "25x cross",
     "liqPx": 1483.3295384256,
     "uPnl": -320061.9706,
     "entryTime": null,
     "entrySince": null
    },
    {
     "coin": "XRP",
     "side": "short",
     "szi": 10500100.0,
     "entryPx": 1.069595,
     "notionalUsd": 11542759.93,
     "leverage": "20x cross",
     "liqPx": 1.6613064777,
     "uPnl": -311901.1875,
     "entryTime": null,
     "entrySince": 1781470770625
    }
   ],
   "rankPnl": 11,
   "rankRoi": 5,
   "changes": {
    "h1": {},
    "h4": {}
   }
  },
  {
   "addr": "0x45d26f28196d226497130c4bac709d808fed4029",
   "name": null,
   "accountValue": 34127143.639934,
   "monthPnl": 3030513.481939,
   "monthRoi": 0.2430724461,
   "positions": [
    {
     "coin": "BTC",
     "side": "short",
     "szi": 229.8,
     "entryPx": 80262.5,
     "notionalUsd": 14892878.4,
     "leverage": "20x cross",
     "liqPx": 151117.3013597954,
     "uPnl": 3551461.609051,
     "entryTime": null,
     "entrySince": null
    },
    {
     "coin": "ETH",
     "side": "short",
     "szi": 5037.0,
     "entryPx": 2385.27,
     "notionalUsd": 9463515.6,
     "leverage": "20x cross",
     "liqPx": 5787.4837638022,
     "uPnl": 2551121.045793,
     "entryTime": null,
     "entrySince": 1778344214504
    },
    {
     "coin": "ATOM",
     "side": "short",
     "szi": 24600.0,
     "entryPx": 10.1735,
     "notionalUsd": 36223.5,
     "leverage": "5x cross",
     "liqPx": 797.8953007391,
     "uPnl": 214045.06346,
     "entryTime": null,
     "entrySince": null
    },
    {
     "coin": "SOL",
     "side": "short",
     "szi": 25120.0,
     "entryPx": 93.5333,
     "notionalUsd": 1925849.92,
     "leverage": "20x cross",
     "liqPx": 856.6023414882,
     "uPnl": 423706.95738,
     "entryTime": null,
     "entrySince": 1778344213403
    },
    {
     "coin": "AVAX",
     "side": "short",
     "szi": 9870.0,
     "entryPx": 49.454,
     "notionalUsd": 65066.001,
     "leverage": "10x cross",
     "liqPx": 1991.5974568574,
     "uPnl": 423045.39119,
     "entryTime": null,
     "entrySince": null
    },
    {
     "coin": "BNB",
     "side": "short",
     "szi": 128.0,
     "entryPx": 697.335,
     "notionalUsd": 72926.72,
     "leverage": "10x cross",
     "liqPx": 144235.6106295241,
     "uPnl": 16332.19437,
     "entryTime": null,
     "entrySince": null
    },
    {
     "coin": "DOGE",
     "side": "short",
     "szi": 6786000.0,
     "entryPx": 0.107053,
     "notionalUsd": 493247.196,
     "leverage": "10x cross",
     "liqPx": 2.8910657062,
     "uPnl": 233219.20821,
     "entryTime": null,
     "entrySince": null
    },
    {
     "coin": "XRP",
     "side": "short",
     "szi": 149000.0,
     "entryPx": 1.419711,
     "notionalUsd": 163795.7,
     "leverage": "20x cross",
     "liqPx": 132.589238914,
     "uPnl": 47741.3337,
     "entryTime": null,
     "entrySince": 1778424878315
    },
    {
     "coin": "TAO",
     "side": "short",
     "szi": 1890.0,
     "entryPx": 321.714,
     "notionalUsd": 371430.36,
     "leverage": "5x cross",
     "liqPx": 9855.8799021823,
     "uPnl": 236610.83139,
     "entryTime": 1778425477313,
     "entrySince": null
    }
   ],
   "rankPnl": 12,
   "rankRoi": 14,
   "changes": {
    "h1": {},
    "h4": {}
   }
  },
  {
   "addr": "0xf822fa0fd364c573fcdb7009fcf47601bc8be01a",
   "name": null,
   "accountValue": 59732304.991915,
   "monthPnl": 2596910.20069,
   "monthRoi": 0.0454518641,
   "positions": [
    {
     "coin": "BTC",
     "side": "short",
     "szi": 855.37017,
     "entryPx": 62236.7,
     "notionalUsd": 55434829.97736,
     "leverage": "3x cross",
     "liqPx": 127752.3315467767,
     "uPnl": -2199392.437439,
     "entryTime": null,
     "entrySince": 1783518773306
    },
    {
     "coin": "ETH",
     "side": "short",
     "szi": 18257.3869,
     "entryPx": 1734.56,
     "notionalUsd": 34301978.50772,
     "leverage": "3x cross",
     "liqPx": 4806.0982131638,
     "uPnl": -2633334.368168,
     "entryTime": null,
     "entrySince": 1783518918696
    },
    {
     "coin": "SOL",
     "side": "short",
     "szi": 141876.66,
     "entryPx": 76.4987,
     "notionalUsd": 10877116.01556,
     "leverage": "3x cross",
     "liqPx": 451.5275849123,
     "uPnl": -23724.474806,
     "entryTime": null,
     "entrySince": 1783519260261
    }
   ],
   "rankPnl": 13,
   "rankRoi": 28,
   "changes": {
    "h1": {},
    "h4": {}
   }
  },
  {
   "addr": "0x939f95036d2e7b6d7419ec072bf9d967352204d2",
   "name": null,
   "accountValue": 18171076.395195,
   "monthPnl": 2573997.259296,
   "monthRoi": 0.4554014503,
   "positions": [
    {
     "coin": "BTC",
     "side": "long",
     "szi": 68.22814,
     "entryPx": 70588.0,
     "notionalUsd": 4421729.29712,
     "leverage": "40x cross",
     "liqPx": 9276.3915320837,
     "uPnl": -394360.440713,
     "entryTime": 1760122104686,
     "entrySince": null
    }
   ],
   "rankPnl": 14,
   "rankRoi": 7,
   "changes": {
    "h1": {},
    "h4": {}
   }
  },
  {
   "addr": "0xfc667adba8d4837586078f4fdcdc29804337ca06",
   "name": null,
   "accountValue": 94637599.10723199,
   "monthPnl": 2405321.957526,
   "monthRoi": 0.0287870127,
   "positions": [
    {
     "coin": "BTC",
     "side": "short",
     "szi": 131.31832,
     "entryPx": 63734.5,
     "notionalUsd": 8510477.68256,
     "leverage": "20x cross",
     "liqPx": 214424.5990288388,
     "uPnl": -140967.446959,
     "entryTime": null,
     "entrySince": 1784483280082
    },
    {
     "coin": "ETH",
     "side": "short",
     "szi": 10004.6198,
     "entryPx": 1798.92,
     "notionalUsd": 18796679.68024,
     "leverage": "20x cross",
     "liqPx": 3828.1928443896,
     "uPnl": -799145.720883,
     "entryTime": null,
     "entrySince": 1784484487466
    },
    {
     "coin": "SOL",
     "side": "short",
     "szi": 95896.41,
     "entryPx": 77.6205,
     "notionalUsd": 7351994.16906,
     "leverage": "20x cross",
     "liqPx": 279.0489461846,
     "uPnl": 91540.651328,
     "entryTime": null,
     "entrySince": 1784484486709
    },
    {
     "coin": "XRP",
     "side": "short",
     "szi": 4276820.0,
     "entryPx": 1.098076,
     "notionalUsd": 4701508.226,
     "leverage": "20x cross",
     "liqPx": 5.6372038595,
     "uPnl": -5230.73604,
     "entryTime": null,
     "entrySince": 1784484214972
    }
   ],
   "rankPnl": 15,
   "rankRoi": 33,
   "changes": {
    "h1": {},
    "h4": {}
   }
  },
  {
   "addr": "0x77375a8c9d13bf79afb2a87f1b0ac1dfd5f5bf66",
   "name": null,
   "accountValue": 32651889.880785003,
   "monthPnl": 2230120.7390900003,
   "monthRoi": 0.5616449027,
   "positions": [
    {
     "coin": "BTC",
     "side": "short",
     "szi": 231.42877,
     "entryPx": 64343.9,
     "notionalUsd": 14998435.72616,
     "leverage": "15x cross",
     "liqPx": 128333.109548,
     "uPnl": -107404.960816,
     "entryTime": null,
     "entrySince": 1753257574605
    },
    {
     "coin": "SOL",
     "side": "short",
     "szi": 45971.64,
     "entryPx": 76.3609,
     "notionalUsd": 3524461.75224,
     "leverage": "10x cross",
     "liqPx": 392.5618635897,
     "uPnl": -14023.22413,
     "entryTime": null,
     "entrySince": 1753496225366
    }
   ],
   "rankPnl": 16,
   "rankRoi": 4,
   "changes": {
    "h1": {},
    "h4": {}
   }
  },
  {
   "addr": "0xc26cbb6483229e0d0f9a1cab675271eda535b8f4",
   "name": null,
   "accountValue": 24019486.271905,
   "monthPnl": 2175960.968867,
   "monthRoi": 0.099615833,
   "positions": [
    {
     "coin": "BTC",
     "side": "long",
     "szi": 79.65619,
     "entryPx": 67243.1,
     "notionalUsd": 5162358.36152,
     "leverage": "2x cross",
     "liqPx": null,
     "uPnl": -193976.04494,
     "entryTime": 1774537145982,
     "entrySince": null
    },
    {
     "coin": "SOL",
     "side": "long",
     "szi": 91276.13,
     "entryPx": 131.022,
     "notionalUsd": 6997775.78258,
     "leverage": "2x cross",
     "liqPx": null,
     "uPnl": -4961413.813739,
     "entryTime": null,
     "entrySince": null
    },
    {
     "coin": "XRP",
     "side": "long",
     "szi": 4014025.0,
     "entryPx": 1.324002,
     "notionalUsd": 4412617.6825,
     "leverage": "1x cross",
     "liqPx": null,
     "uPnl": -901959.8818,
     "entryTime": null,
     "entrySince": null
    }
   ],
   "rankPnl": 17,
   "rankRoi": 21,
   "changes": {
    "h1": {},
    "h4": {}
   }
  },
  {
   "addr": "0xa98143608a6846453c88f29506d64a8b85532e65",
   "name": null,
   "accountValue": 15976060.438692,
   "monthPnl": 2025692.302971,
   "monthRoi": 0.5236220144,
   "positions": [
    {
     "coin": "ETH",
     "side": "short",
     "szi": 739.0,
     "entryPx": 2046.49,
     "notionalUsd": 1388433.2,
     "leverage": "20x cross",
     "liqPx": 12824.4071984385,
     "uPnl": 123926.944385,
     "entryTime": null,
     "entrySince": 1776581755220
    },
    {
     "coin": "SOL",
     "side": "short",
     "szi": 310.1,
     "entryPx": 89.515,
     "notionalUsd": 23774.1266,
     "leverage": "20x cross",
     "liqPx": 26033.9254018892,
     "uPnl": 3984.4749,
     "entryTime": 1773997784790,
     "entrySince": null
    }
   ],
   "rankPnl": 18,
   "rankRoi": 6,
   "changes": {
    "h1": {},
    "h4": {}
   }
  },
  {
   "addr": "0x856c35038594767646266bc7fd68dc26480e910d",
   "name": null,
   "accountValue": 71447192.64887801,
   "monthPnl": 1745551.5428649997,
   "monthRoi": 0.0389870488,
   "positions": [
    {
     "coin": "BTC",
     "side": "long",
     "szi": 9.34087,
     "entryPx": 60570.1,
     "notionalUsd": 605363.10296,
     "leverage": "20x cross",
     "liqPx": null,
     "uPnl": 39584.79293,
     "entryTime": null,
     "entrySince": null
    },
    {
     "coin": "ETH",
     "side": "short",
     "szi": 28.3584,
     "entryPx": 1676.34,
     "notionalUsd": 53279.76192,
     "leverage": "20x cross",
     "liqPx": 183385.5927661991,
     "uPnl": -5741.30215,
     "entryTime": null,
     "entrySince": null
    },
    {
     "coin": "SOL",
     "side": "long",
     "szi": 827.66,
     "entryPx": 80.9431,
     "notionalUsd": 63453.38156,
     "leverage": "20x cross",
     "liqPx": null,
     "uPnl": -3540.01393,
     "entryTime": null,
     "entrySince": null
    },
    {
     "coin": "BNB",
     "side": "short",
     "szi": 280.13,
     "entryPx": 579.392,
     "notionalUsd": 159601.2662,
     "leverage": "5x cross",
     "liqPx": 18068.7810728493,
     "uPnl": 2703.91198,
     "entryTime": null,
     "entrySince": 1783691192171
    },
    {
     "coin": "DOGE",
     "side": "short",
     "szi": 85.0,
     "entryPx": 0.090679,
     "notionalUsd": 6.17831,
     "leverage": "10x cross",
     "liqPx": 58825.6981943529,
     "uPnl": 1.529405,
     "entryTime": null,
     "entrySince": null
    },
    {
     "coin": "XRP",
     "side": "short",
     "szi": 298.0,
     "entryPx": 1.081744,
     "notionalUsd": 327.5914,
     "leverage": "10x cross",
     "liqPx": 17189.4675325127,
     "uPnl": -5.23141,
     "entryTime": null,
     "entrySince": null
    },
    {
     "coin": "TAO",
     "side": "long",
     "szi": 147.359,
     "entryPx": 244.396,
     "notionalUsd": 28959.580116,
     "leverage": "5x cross",
     "liqPx": null,
     "uPnl": -7054.505284,
     "entryTime": null,
     "entrySince": null
    }
   ],
   "rankPnl": 19,
   "rankRoi": 30,
   "changes": {
    "h1": {},
    "h4": {}
   }
  },
  {
   "addr": "0x960b6c2c4b1498681b8422eb572a8b3a6aa3f0fc",
   "name": null,
   "accountValue": 17756540.880769,
   "monthPnl": 1662305.986079,
   "monthRoi": 0.1031614528,
   "positions": [
    {
     "coin": "ETH",
     "side": "short",
     "szi": 1081.4693,
     "entryPx": 1849.2,
     "notionalUsd": 2031864.52084,
     "leverage": "6x cross",
     "liqPx": 8057.4906474968,
     "uPnl": -32009.9665,
     "entryTime": 1758158624526,
     "entrySince": null
    }
   ],
   "rankPnl": 20,
   "rankRoi": 20,
   "changes": {
    "h1": {},
    "h4": {}
   }
  },
  {
   "addr": "0xaf0fdd39e5d92499b0ed9f68693da99c0ec1e92e",
   "name": null,
   "accountValue": 11485968.632091,
   "monthPnl": 1119434.066604,
   "monthRoi": 0.2933481777,
   "positions": [
    {
     "coin": "BTC",
     "side": "short",
     "szi": 88.0,
     "entryPx": 64742.1,
     "notionalUsd": 5703104.0,
     "leverage": "30x cross",
     "liqPx": 106818.6306413468,
     "uPnl": -5791.90976,
     "entryTime": 1761058760258,
     "entrySince": null
    }
   ],
   "rankPnl": 26,
   "rankRoi": 10,
   "changes": {
    "h1": {},
    "h4": {}
   }
  },
  {
   "addr": "0xcac19662ec88d23fa1c81ac0e8570b0cf2ff26b3",
   "name": null,
   "accountValue": 21274859.603226997,
   "monthPnl": 1166623.439931,
   "monthRoi": 0.2640611932,
   "positions": [
    {
     "coin": "BTC",
     "side": "short",
     "szi": 104.66857,
     "entryPx": 61787.7,
     "notionalUsd": 6783360.68456,
     "leverage": "20x cross",
     "liqPx": 155141.7612054677,
     "uPnl": -316127.77004,
     "entryTime": null,
     "entrySince": null
    },
    {
     "coin": "ETH",
     "side": "short",
     "szi": 1551.8588,
     "entryPx": 1757.92,
     "notionalUsd": 2915632.31344,
     "leverage": "20x cross",
     "liqPx": 7926.7618202013,
     "uPnl": -187579.43527,
     "entryTime": null,
     "entrySince": null
    },
    {
     "coin": "SOL",
     "side": "short",
     "szi": 32296.86,
     "entryPx": 73.747,
     "notionalUsd": 2476071.06876,
     "leverage": "20x cross",
     "liqPx": 365.8519902834,
     "uPnl": -94274.138074,
     "entryTime": null,
     "entrySince": null
    },
    {
     "coin": "AVAX",
     "side": "long",
     "szi": 71886.42,
     "entryPx": 6.4048,
     "notionalUsd": 473896.846566,
     "leverage": "10x cross",
     "liqPx": null,
     "uPnl": 13474.487503,
     "entryTime": null,
     "entrySince": null
    },
    {
     "coin": "BNB",
     "side": "short",
     "szi": 300.0,
     "entryPx": 572.973,
     "notionalUsd": 170922.0,
     "leverage": "10x cross",
     "liqPx": 30008.3712975727,
     "uPnl": 970.13774,
     "entryTime": null,
     "entrySince": null
    },
    {
     "coin": "DOGE",
     "side": "long",
     "szi": 996620.0,
     "entryPx": 0.084106,
     "notionalUsd": 72440.32132,
     "leverage": "10x cross",
     "liqPx": null,
     "uPnl": -11382.16952,
     "entryTime": null,
     "entrySince": null
    },
    {
     "coin": "XRP",
     "side": "long",
     "szi": 704888.0,
     "entryPx": 1.371665,
     "notionalUsd": 774883.3784,
     "leverage": "20x cross",
     "liqPx": null,
     "uPnl": -191987.390288,
     "entryTime": null,
     "entrySince": null
    },
    {
     "coin": "TAO",
     "side": "short",
     "szi": 789.82,
     "entryPx": 288.282,
     "notionalUsd": 155218.58568,
     "leverage": "5x cross",
     "liqPx": 11215.4839335625,
     "uPnl": 72472.953952,
     "entryTime": null,
     "entrySince": null
    }
   ],
   "rankPnl": 24,
   "rankRoi": 12,
   "changes": {
    "h1": {},
    "h4": {}
   }
  },
  {
   "addr": "0x3bcae23e8c380dab4732e9a159c0456f12d866f3",
   "name": null,
   "accountValue": 11170418.061255,
   "monthPnl": 565177.855383,
   "monthRoi": 0.2312788927,
   "positions": [
    {
     "coin": "ETH",
     "side": "short",
     "szi": 2193.2418,
     "entryPx": 1878.15,
     "notionalUsd": 4120662.69384,
     "leverage": "25x cross",
     "liqPx": 6704.4149227364,
     "uPnl": -1409.412598,
     "entryTime": 1784093329576,
     "entrySince": null
    }
   ],
   "rankPnl": 30,
   "rankRoi": 16,
   "changes": {
    "h1": {},
    "h4": {}
   }
  },
  {
   "addr": "0x8af700ba841f30e0a3fcb0ee4c4a9d223e1efa05",
   "name": null,
   "accountValue": 23439043.027424,
   "monthPnl": 1134577.440212,
   "monthRoi": 0.1244753644,
   "positions": [
    {
     "coin": "BTC",
     "side": "long",
     "szi": 41.13883,
     "entryPx": 70834.4,
     "notionalUsd": 2666125.29464,
     "leverage": "40x cross",
     "liqPx": null,
     "uPnl": -247919.625751,
     "entryTime": null,
     "entrySince": null
    },
    {
     "coin": "ETH",
     "side": "long",
     "szi": 37.4459,
     "entryPx": 1844.48,
     "notionalUsd": 70353.35692,
     "leverage": "25x cross",
     "liqPx": null,
     "uPnl": 1285.077821,
     "entryTime": null,
     "entrySince": null
    },
    {
     "coin": "AVAX",
     "side": "short",
     "szi": 12091.83,
     "entryPx": 42.1163,
     "notionalUsd": 79712.970909,
     "leverage": "10x cross",
     "liqPx": 1570.2137717173,
     "uPnl": 429551.339941,
     "entryTime": null,
     "entrySince": null
    },
    {
     "coin": "XRP",
     "side": "short",
     "szi": 690000.0,
     "entryPx": 1.494361,
     "notionalUsd": 758517.0,
     "leverage": "20x cross",
     "liqPx": 28.5008145223,
     "uPnl": 272592.4156,
     "entryTime": null,
     "entrySince": null
    }
   ],
   "rankPnl": 25,
   "rankRoi": 19,
   "changes": {
    "h1": {},
    "h4": {}
   }
  }
 ],
 "aggregates": [
  {
   "coin": "ETH",
   "long": 6,
   "short": 12,
   "longNotional": 290603070.04036003,
   "shortNotional": 174681633.28615996,
   "totalNotional": 465284703.32651997,
   "score": 25
  },
  {
   "coin": "BTC",
   "long": 7,
   "short": 9,
   "longNotional": 33260192.74576,
   "shortNotional": 189031810.43576,
   "totalNotional": 222292003.18152,
   "score": -70
  },
  {
   "coin": "SOL",
   "long": 4,
   "short": 8,
   "longNotional": 7062207.4223,
   "shortNotional": 49121008.65708,
   "totalNotional": 56183216.079380006,
   "score": -75
  },
  {
   "coin": "XRP",
   "long": 3,
   "short": 6,
   "longNotional": 5200097.9396,
   "shortNotional": 17440890.2843,
   "totalNotional": 22640988.223899998,
   "score": -54
  },
  {
   "coin": "AVAX",
   "long": 1,
   "short": 3,
   "longNotional": 473896.846566,
   "shortNotional": 144781.674752,
   "totalNotional": 618678.521318,
   "score": 53
  },
  {
   "coin": "DOGE",
   "long": 1,
   "short": 3,
   "longNotional": 72440.32132,
   "shortNotional": 493253.446996,
   "totalNotional": 565693.768316,
   "score": -74
  },
  {
   "coin": "TAO",
   "long": 1,
   "short": 2,
   "longNotional": 28959.580116,
   "shortNotional": 526648.94568,
   "totalNotional": 555608.525796,
   "score": -90
  },
  {
   "coin": "BNB",
   "long": 0,
   "short": 3,
   "longNotional": 0.0,
   "shortNotional": 403449.98620000004,
   "totalNotional": 403449.98620000004,
   "score": -100
  },
  {
   "coin": "ATOM",
   "long": 0,
   "short": 1,
   "longNotional": 0.0,
   "shortNotional": 36223.5,
   "totalNotional": 36223.5,
   "score": -100
  }
 ]
}