{
 "generatedAt": "2026-07-01T05:01:05+00:00",
 "generatedAtMs": 1782882057660,
 "window": "month",
 "topN": 20,
 "minAccount": 10000000,
 "focus": [
  "BTC",
  "ETH",
  "ATOM",
  "TAO",
  "XRP",
  "SOL",
  "BNB",
  "DOGE",
  "AVAX"
 ],
 "traders": [
  {
   "addr": "0x0ddf9bae2af4b874b96d287a5ad42eb47138a902",
   "name": "Penision Fund",
   "accountValue": 31025656.379319,
   "monthPnl": 22571454.242967,
   "monthRoi": 0.6835902007,
   "positions": [
    {
     "coin": "ETH",
     "side": "short",
     "szi": 50000.0,
     "entryPx": 1700.06,
     "notionalUsd": 79895000.0,
     "leverage": "3x cross",
     "liqPx": 2168.7088540084,
     "uPnl": 5108349.154357,
     "entryTime": null,
     "entrySince": 1780493327090
    }
   ],
   "rankPnl": 1,
   "rankRoi": 7,
   "changes": {
    "h1": {},
    "h4": {}
   }
  },
  {
   "addr": "0x7fdafde5cfb5465924316eced2d3715494c517d1",
   "name": "BobbyBigSize",
   "accountValue": 29680524.195955,
   "monthPnl": 18026183.941016003,
   "monthRoi": 0.4721468747,
   "positions": [
    {
     "coin": "BTC",
     "side": "long",
     "szi": 175.04688,
     "entryPx": 58965.5,
     "notionalUsd": 10377304.18704,
     "leverage": "20x cross",
     "liqPx": null,
     "uPnl": 55563.329622,
     "entryTime": null,
     "entrySince": 1782835415227
    },
    {
     "coin": "ETH",
     "side": "short",
     "szi": 5896.4998,
     "entryPx": 1655.67,
     "notionalUsd": 9422017.03042,
     "leverage": "15x cross",
     "liqPx": 3796.1475505987,
     "uPnl": 340643.694714,
     "entryTime": null,
     "entrySince": 1782835816130
    },
    {
     "coin": "SOL",
     "side": "short",
     "szi": 5612.89,
     "entryPx": 75.0391,
     "notionalUsd": 424177.32308,
     "leverage": "20x cross",
     "liqPx": 2373.6282845226,
     "uPnl": -2990.92877,
     "entryTime": null,
     "entrySince": 1782835564638
    },
    {
     "coin": "AVAX",
     "side": "short",
     "szi": 438786.05,
     "entryPx": 13.2086,
     "notionalUsd": 2938725.69127,
     "leverage": "10x cross",
     "liqPx": 35.393901062,
     "uPnl": 2857038.127554,
     "entryTime": null,
     "entrySince": 1782835693853
    },
    {
     "coin": "BNB",
     "side": "short",
     "szi": 1553.193,
     "entryPx": 763.004,
     "notionalUsd": 855467.64054,
     "leverage": "10x cross",
     "liqPx": 8351.9718235988,
     "uPnl": 329626.330625,
     "entryTime": null,
     "entrySince": null
    },
    {
     "coin": "DOGE",
     "side": "short",
     "szi": 32919008.0,
     "entryPx": 0.105872,
     "notionalUsd": 2386233.051904,
     "leverage": "10x cross",
     "liqPx": 0.4549911529,
     "uPnl": 1098975.740143,
     "entryTime": null,
     "entrySince": 1782835418666
    },
    {
     "coin": "XRP",
     "side": "long",
     "szi": 2292389.0,
     "entryPx": 1.091719,
     "notionalUsd": 2409530.0779,
     "leverage": "20x cross",
     "liqPx": null,
     "uPnl": -93116.008944,
     "entryTime": null,
     "entrySince": 1782839094987
    },
    {
     "coin": "TAO",
     "side": "short",
     "szi": 1671.649,
     "entryPx": 259.298,
     "notionalUsd": 340732.21567,
     "leverage": "5x cross",
     "liqPx": 7393.9026698362,
     "uPnl": 92723.840708,
     "entryTime": null,
     "entrySince": 1782836150853
    }
   ],
   "rankPnl": 2,
   "rankRoi": 11,
   "changes": {
    "h1": {},
    "h4": {}
   }
  },
  {
   "addr": "0xfc667adba8d4837586078f4fdcdc29804337ca06",
   "name": null,
   "accountValue": 63753115.337723,
   "monthPnl": 13075935.057254,
   "monthRoi": 0.1448015037,
   "positions": [
    {
     "coin": "BTC",
     "side": "short",
     "szi": 51.59154,
     "entryPx": 59520.9,
     "notionalUsd": 3058501.26582,
     "leverage": "20x cross",
     "liqPx": 157195.574618055,
     "uPnl": 12274.322046,
     "entryTime": null,
     "entrySince": 1782840730167
    },
    {
     "coin": "ETH",
     "side": "short",
     "szi": 1769.0656,
     "entryPx": 1564.61,
     "notionalUsd": 2826789.92224,
     "leverage": "20x cross",
     "liqPx": 4432.3440239671,
     "uPnl": -58879.494951,
     "entryTime": null,
     "entrySince": 1782842402276
    },
    {
     "coin": "SOL",
     "side": "short",
     "szi": 51105.7,
     "entryPx": 74.5253,
     "notionalUsd": 3862159.9604,
     "leverage": "20x cross",
     "liqPx": 173.2099803615,
     "uPnl": -53488.404305,
     "entryTime": null,
     "entrySince": null
    },
    {
     "coin": "XRP",
     "side": "short",
     "szi": 200943.0,
     "entryPx": 1.096049,
     "notionalUsd": 211211.1873,
     "leverage": "20x cross",
     "liqPx": 25.8833028285,
     "uPnl": 9032.311926,
     "entryTime": null,
     "entrySince": null
    }
   ],
   "rankPnl": 3,
   "rankRoi": 24,
   "changes": {
    "h1": {},
    "h4": {}
   }
  },
  {
   "addr": "0x17c3c8fdbcb7d1b240ce08965e09b1fc91cba868",
   "name": null,
   "accountValue": 23720186.994598,
   "monthPnl": 12766156.650814,
   "monthRoi": 0.3515817359,
   "positions": [
    {
     "coin": "BTC",
     "side": "long",
     "szi": 4.34665,
     "entryPx": 60116.3,
     "notionalUsd": 257682.45195,
     "leverage": "3x cross",
     "liqPx": null,
     "uPnl": -3622.156345,
     "entryTime": null,
     "entrySince": 1782483756282
    },
    {
     "coin": "ETH",
     "side": "short",
     "szi": 89.8712,
     "entryPx": 1600.61,
     "notionalUsd": 143605.19048,
     "leverage": "3x cross",
     "liqPx": 27619.0150497841,
     "uPnl": 243.764029,
     "entryTime": null,
     "entrySince": 1782483896885
    }
   ],
   "rankPnl": 4,
   "rankRoi": 17,
   "changes": {
    "h1": {},
    "h4": {}
   }
  },
  {
   "addr": "0xf822fa0fd364c573fcdb7009fcf47601bc8be01a",
   "name": null,
   "accountValue": 37383837.12366,
   "monthPnl": 12453296.390742,
   "monthRoi": 0.4160960511,
   "positions": [
    {
     "coin": "BTC",
     "side": "short",
     "szi": 758.20478,
     "entryPx": 62170.3,
     "notionalUsd": 44948653.97274,
     "leverage": "3x cross",
     "liqPx": 102612.0493609219,
     "uPnl": 2189165.192884,
     "entryTime": null,
     "entrySince": 1782831570010
    },
    {
     "coin": "ETH",
     "side": "short",
     "szi": 9493.7827,
     "entryPx": 1699.72,
     "notionalUsd": 15170115.37633,
     "leverage": "3x cross",
     "liqPx": 5032.856581135,
     "uPnl": 966686.270681,
     "entryTime": null,
     "entrySince": null
    },
    {
     "coin": "SOL",
     "side": "short",
     "szi": 45151.96,
     "entryPx": 73.5946,
     "notionalUsd": 3412223.92112,
     "leverage": "3x cross",
     "liqPx": 794.2928401776,
     "uPnl": -89280.729843,
     "entryTime": null,
     "entrySince": 1782831578000
    }
   ],
   "rankPnl": 5,
   "rankRoi": 14,
   "changes": {
    "h1": {},
    "h4": {}
   }
  },
  {
   "addr": "0xecb63caa47c7c4e77f60f1ce858cf28dc2b82b00",
   "name": null,
   "accountValue": 85365773.024486,
   "monthPnl": 12312971.113722,
   "monthRoi": 0.1101992525,
   "positions": [
    {
     "coin": "BTC",
     "side": "long",
     "szi": 198.40774,
     "entryPx": 58343.1,
     "notionalUsd": 11762206.05042,
     "leverage": "20x cross",
     "liqPx": null,
     "uPnl": 186481.090263,
     "entryTime": null,
     "entrySince": 1782870493000
    },
    {
     "coin": "ETH",
     "side": "short",
     "szi": 14729.4042,
     "entryPx": 1575.87,
     "notionalUsd": 23536114.97118,
     "leverage": "15x cross",
     "liqPx": 3167.6404664437,
     "uPnl": -324346.491682,
     "entryTime": null,
     "entrySince": 1782870487392
    },
    {
     "coin": "ATOM",
     "side": "long",
     "szi": 76440.93,
     "entryPx": 1.6897,
     "notionalUsd": 116916.402435,
     "leverage": "5x cross",
     "liqPx": null,
     "uPnl": -12251.572848,
     "entryTime": null,
     "entrySince": null
    },
    {
     "coin": "SOL",
     "side": "short",
     "szi": 174991.59,
     "entryPx": 73.0995,
     "notionalUsd": 13224464.43948,
     "leverage": "20x cross",
     "liqPx": 207.055774655,
     "uPnl": -432656.631572,
     "entryTime": null,
     "entrySince": 1782870462033
    },
    {
     "coin": "AVAX",
     "side": "long",
     "szi": 24467.79,
     "entryPx": 6.4264,
     "notionalUsd": 163870.576746,
     "leverage": "10x cross",
     "liqPx": null,
     "uPnl": 6628.84541,
     "entryTime": null,
     "entrySince": 1782871568138
    },
    {
     "coin": "BNB",
     "side": "short",
     "szi": 847.769,
     "entryPx": 554.881,
     "notionalUsd": 466934.20982,
     "leverage": "5x cross",
     "liqPx": 25976.2544407144,
     "uPnl": 3476.842365,
     "entryTime": null,
     "entrySince": 1782870679874
    },
    {
     "coin": "DOGE",
     "side": "short",
     "szi": 15492251.0,
     "entryPx": 0.075498,
     "notionalUsd": 1123002.290488,
     "leverage": "10x cross",
     "liqPx": 1.5117775543,
     "uPnl": 46639.898289,
     "entryTime": null,
     "entrySince": 1782870670961
    },
    {
     "coin": "XRP",
     "side": "short",
     "szi": 2997265.0,
     "entryPx": 1.045554,
     "notionalUsd": 3150425.2415,
     "leverage": "10x cross",
     "liqPx": 8.7276166864,
     "uPnl": -16622.317773,
     "entryTime": null,
     "entrySince": 1782871286294
    },
    {
     "coin": "TAO",
     "side": "short",
     "szi": 2073.014,
     "entryPx": 213.146,
     "notionalUsd": 422542.44362,
     "leverage": "5x cross",
     "liqPx": 10546.1574937028,
     "uPnl": 19313.37822,
     "entryTime": null,
     "entrySince": 1782870608653
    }
   ],
   "rankPnl": 6,
   "rankRoi": 25,
   "changes": {
    "h1": {},
    "h4": {
     "SOL": {
      "openedSz": 947.2,
      "closedSz": 105.7,
      "n": 45,
      "lastTime": 1782872214010
     },
     "ETH": {
      "openedSz": 0.0,
      "closedSz": 415.8739,
      "n": 51,
      "lastTime": 1782872081104
     },
     "BTC": {
      "openedSz": 5.11862,
      "closedSz": 2.55495,
      "n": 7,
      "lastTime": 1782871595289
     },
     "TAO": {
      "openedSz": 1.499,
      "closedSz": 43.968,
      "n": 31,
      "lastTime": 1782872141704
     },
     "DOGE": {
      "openedSz": 517.0,
      "closedSz": 59108.0,
      "n": 6,
      "lastTime": 1782872167581
     },
     "BNB": {
      "openedSz": 2.0189999999999997,
      "closedSz": 0.0,
      "n": 5,
      "lastTime": 1782872038097
     },
     "XRP": {
      "openedSz": 240.0,
      "closedSz": 1875.0,
      "n": 5,
      "lastTime": 1782871843402
     },
     "AVAX": {
      "openedSz": 0.0,
      "closedSz": 0.41,
      "n": 1,
      "lastTime": 1782871568138
     }
    }
   }
  },
  {
   "addr": "0xb83de012dba672c76a7dbbbf3e459cb59d7d6e36",
   "name": null,
   "accountValue": 91548942.955227,
   "monthPnl": 11113771.658419,
   "monthRoi": 0.5269144235,
   "positions": [
    {
     "coin": "BTC",
     "side": "long",
     "szi": 0.62802,
     "entryPx": 71584.6,
     "notionalUsd": 37230.90966,
     "leverage": "5x cross",
     "liqPx": null,
     "uPnl": -7725.705443,
     "entryTime": null,
     "entrySince": null
    },
    {
     "coin": "ETH",
     "side": "long",
     "szi": 0.5563,
     "entryPx": 1667.9,
     "notionalUsd": 888.91177,
     "leverage": "10x cross",
     "liqPx": null,
     "uPnl": -38.941,
     "entryTime": null,
     "entrySince": null
    },
    {
     "coin": "SOL",
     "side": "short",
     "szi": 733.91,
     "entryPx": 91.5472,
     "notionalUsd": 55463.04652,
     "leverage": "4x cross",
     "liqPx": 28772.4757560876,
     "uPnl": 11724.388114,
     "entryTime": null,
     "entrySince": null
    },
    {
     "coin": "AVAX",
     "side": "short",
     "szi": 0.41,
     "entryPx": 6.5726,
     "notionalUsd": 2.745934,
     "leverage": "10x cross",
     "liqPx": 50083084.55598891,
     "uPnl": -0.051168,
     "entryTime": null,
     "entrySince": null
    },
    {
     "coin": "DOGE",
     "side": "short",
     "szi": 1.0,
     "entryPx": 0.107181,
     "notionalUsd": 0.072488,
     "leverage": "10x cross",
     "liqPx": 20534062.11603,
     "uPnl": 0.034693,
     "entryTime": null,
     "entrySince": null
    },
    {
     "coin": "XRP",
     "side": "long",
     "szi": 11459.0,
     "entryPx": 1.394549,
     "notionalUsd": 12044.5549,
     "leverage": "5x cross",
     "liqPx": null,
     "uPnl": -3935.5847,
     "entryTime": null,
     "entrySince": null
    }
   ],
   "rankPnl": 7,
   "rankRoi": 10,
   "changes": {
    "h1": {},
    "h4": {}
   }
  },
  {
   "addr": "0x45d26f28196d226497130c4bac709d808fed4029",
   "name": null,
   "accountValue": 32586651.615971,
   "monthPnl": 8339555.874816,
   "monthRoi": 0.6141660661,
   "positions": [
    {
     "coin": "BTC",
     "side": "short",
     "szi": 103.0,
     "entryPx": 100172.5,
     "notionalUsd": 6106149.0,
     "leverage": "20x cross",
     "liqPx": 227704.7689642383,
     "uPnl": 4211626.759551,
     "entryTime": null,
     "entrySince": null
    },
    {
     "coin": "ETH",
     "side": "short",
     "szi": 5037.0,
     "entryPx": 2385.27,
     "notionalUsd": 8048622.3,
     "leverage": "20x cross",
     "liqPx": 5016.5792696512,
     "uPnl": 3966014.345793,
     "entryTime": null,
     "entrySince": 1778341159844
    },
    {
     "coin": "ATOM",
     "side": "short",
     "szi": 24600.0,
     "entryPx": 10.1735,
     "notionalUsd": 37625.7,
     "leverage": "5x cross",
     "liqPx": 698.1103142319,
     "uPnl": 212642.86346,
     "entryTime": null,
     "entrySince": null
    },
    {
     "coin": "SOL",
     "side": "short",
     "szi": 25120.0,
     "entryPx": 93.5333,
     "notionalUsd": 1898368.64,
     "leverage": "20x cross",
     "liqPx": 757.7331476953,
     "uPnl": 451188.23738,
     "entryTime": 1778343105547,
     "entrySince": null
    },
    {
     "coin": "AVAX",
     "side": "short",
     "szi": 9870.0,
     "entryPx": 49.454,
     "notionalUsd": 66103.338,
     "leverage": "10x cross",
     "liqPx": 1742.8562682984,
     "uPnl": 422008.05419,
     "entryTime": null,
     "entrySince": null
    },
    {
     "coin": "BNB",
     "side": "short",
     "szi": 128.0,
     "entryPx": 697.335,
     "notionalUsd": 70499.84,
     "leverage": "10x cross",
     "liqPx": 126337.4294237074,
     "uPnl": 18759.07437,
     "entryTime": null,
     "entrySince": null
    },
    {
     "coin": "DOGE",
     "side": "short",
     "szi": 6786000.0,
     "entryPx": 0.107053,
     "notionalUsd": 491903.568,
     "leverage": "10x cross",
     "liqPx": 2.5375470475,
     "uPnl": 234562.83621,
     "entryTime": null,
     "entrySince": null
    },
    {
     "coin": "XRP",
     "side": "short",
     "szi": 149000.0,
     "entryPx": 1.419711,
     "notionalUsd": 156613.9,
     "leverage": "20x cross",
     "liqPx": 116.0570599336,
     "uPnl": 54923.1337,
     "entryTime": 1778343045084,
     "entrySince": null
    },
    {
     "coin": "TAO",
     "side": "short",
     "szi": 1890.0,
     "entryPx": 321.714,
     "notionalUsd": 385238.7,
     "leverage": "5x cross",
     "liqPx": 8652.2596444723,
     "uPnl": 222802.49139,
     "entryTime": null,
     "entrySince": null
    }
   ],
   "rankPnl": 8,
   "rankRoi": 8,
   "changes": {
    "h1": {},
    "h4": {}
   }
  },
  {
   "addr": "0xcf90cfecf74e631feea816d02e757c0c8e895c0e",
   "name": null,
   "accountValue": 16549322.901399,
   "monthPnl": 7689560.574032,
   "monthRoi": 0.8679195096,
   "positions": [
    {
     "coin": "BTC",
     "side": "short",
     "szi": 763.47463,
     "entryPx": 68858.8,
     "notionalUsd": 45261066.49029,
     "leverage": "15x isolated",
     "liqPx": 79792.6125140689,
     "uPnl": 7310886.29391,
     "entryTime": null,
     "entrySince": null
    }
   ],
   "rankPnl": 9,
   "rankRoi": 3,
   "changes": {
    "h1": {},
    "h4": {}
   }
  },
  {
   "addr": "0xfc27136e42af1732ddc9ce2605ea9bff1b959d9d",
   "name": null,
   "accountValue": 16694417.882325,
   "monthPnl": 7625044.725662,
   "monthRoi": 0.304342474,
   "positions": [
    {
     "coin": "BTC",
     "side": "short",
     "szi": 12.60622,
     "entryPx": 59131.5,
     "notionalUsd": 747334.54026,
     "leverage": "10x cross",
     "liqPx": 398166.5958833451,
     "uPnl": -1909.584748,
     "entryTime": null,
     "entrySince": 1782829317765
    }
   ],
   "rankPnl": 10,
   "rankRoi": 19,
   "changes": {
    "h1": {},
    "h4": {}
   }
  },
  {
   "addr": "0x32008fcb6bbd16532afc83ca8b6c920dde22c407",
   "name": null,
   "accountValue": 14257517.292586,
   "monthPnl": 7596140.142491,
   "monthRoi": 0.8031704321,
   "positions": [
    {
     "coin": "BTC",
     "side": "long",
     "szi": 332.51611,
     "entryPx": 60133.3,
     "notionalUsd": 19712552.54913,
     "leverage": "21x cross",
     "liqPx": 29079.7031259978,
     "uPnl": -282740.61388,
     "entryTime": null,
     "entrySince": null
    }
   ],
   "rankPnl": 11,
   "rankRoi": 4,
   "changes": {
    "h1": {},
    "h4": {}
   }
  },
  {
   "addr": "0xa312114b5795dff9b8db50474dd57701aa78ad1e",
   "name": null,
   "accountValue": 26299269.283659,
   "monthPnl": 6073511.794114,
   "monthRoi": 0.4684272466,
   "positions": [
    {
     "coin": "SOL",
     "side": "short",
     "szi": 4666.75,
     "entryPx": 75.6964,
     "notionalUsd": 352675.631,
     "leverage": "20x cross",
     "liqPx": 1879.086441971,
     "uPnl": 580.76078,
     "entryTime": null,
     "entrySince": null
    }
   ],
   "rankPnl": 12,
   "rankRoi": 12,
   "changes": {
    "h1": {},
    "h4": {}
   }
  },
  {
   "addr": "0x77375a8c9d13bf79afb2a87f1b0ac1dfd5f5bf66",
   "name": null,
   "accountValue": 37857202.261903,
   "monthPnl": 5246758.015369,
   "monthRoi": 1.0216470246,
   "positions": [
    {
     "coin": "SOL",
     "side": "short",
     "szi": 54861.99,
     "entryPx": 73.2182,
     "notionalUsd": 4146030.30828,
     "leverage": "10x cross",
     "liqPx": 399.6875213865,
     "uPnl": -129134.05713,
     "entryTime": null,
     "entrySince": 1752078241676
    }
   ],
   "rankPnl": 13,
   "rankRoi": 2,
   "changes": {
    "h1": {},
    "h4": {}
   }
  },
  {
   "addr": "0x936cf4fb95c30ce83f658b5bbb247e4bb381bb0f",
   "name": null,
   "accountValue": 10795218.712066,
   "monthPnl": 4507466.403433,
   "monthRoi": 0.2344665621,
   "positions": [
    {
     "coin": "BTC",
     "side": "long",
     "szi": 89.17064,
     "entryPx": 59895.8,
     "notionalUsd": 5286303.05112,
     "leverage": "20x cross",
     "liqPx": null,
     "uPnl": -54650.021227,
     "entryTime": null,
     "entrySince": 1782743046054
    },
    {
     "coin": "ETH",
     "side": "short",
     "szi": 2528.0065,
     "entryPx": 1681.85,
     "notionalUsd": 4039501.58635,
     "leverage": "20x cross",
     "liqPx": 3626.5937083247,
     "uPnl": 212228.664507,
     "entryTime": null,
     "entrySince": 1782744558753
    },
    {
     "coin": "SOL",
     "side": "short",
     "szi": 11592.58,
     "entryPx": 70.5104,
     "notionalUsd": 876074.45576,
     "leverage": "20x cross",
     "liqPx": 515.8133923201,
     "uPnl": -58675.901059,
     "entryTime": null,
     "entrySince": 1782749517755
    },
    {
     "coin": "XRP",
     "side": "long",
     "szi": 230668.0,
     "entryPx": 1.141384,
     "notionalUsd": 242455.1348,
     "leverage": "20x cross",
     "liqPx": null,
     "uPnl": -20825.63224,
     "entryTime": null,
     "entrySince": 1782743445103
    },
    {
     "coin": "TAO",
     "side": "short",
     "szi": 0.4,
     "entryPx": 278.473,
     "notionalUsd": 81.532,
     "leverage": "5x cross",
     "liqPx": 11889117.236311361,
     "uPnl": 29.85728,
     "entryTime": null,
     "entrySince": null
    }
   ],
   "rankPnl": 14,
   "rankRoi": 21,
   "changes": {
    "h1": {},
    "h4": {}
   }
  },
  {
   "addr": "0x5b5d51203a0f9079f8aeb098a6523a13f298c060",
   "name": null,
   "accountValue": 30608663.87828,
   "monthPnl": 4442563.0724,
   "monthRoi": 0.4530290742,
   "positions": [
    {
     "coin": "BTC",
     "side": "long",
     "szi": 14.89702,
     "entryPx": 61867.1,
     "notionalUsd": 883140.03666,
     "leverage": "10x cross",
     "liqPx": null,
     "uPnl": -38496.614843,
     "entryTime": null,
     "entrySince": 1781449428584
    },
    {
     "coin": "ETH",
     "side": "long",
     "szi": 0.7856,
     "entryPx": 1592.25,
     "notionalUsd": 1255.31024,
     "leverage": "10x cross",
     "liqPx": null,
     "uPnl": 4.43296,
     "entryTime": null,
     "entrySince": null
    },
    {
     "coin": "SOL",
     "side": "short",
     "szi": 27038.1,
     "entryPx": 81.1168,
     "notionalUsd": 2043323.2932,
     "leverage": "10x cross",
     "liqPx": 395.4481312647,
     "uPnl": 149923.189549,
     "entryTime": null,
     "entrySince": null
    },
    {
     "coin": "AVAX",
     "side": "short",
     "szi": 17654.0,
     "entryPx": 9.5279,
     "notionalUsd": 118235.8996,
     "leverage": "5x cross",
     "liqPx": 484.9413104785,
     "uPnl": 49970.635459,
     "entryTime": null,
     "entrySince": null
    },
    {
     "coin": "XRP",
     "side": "short",
     "szi": 249233.0,
     "entryPx": 1.901026,
     "notionalUsd": 261968.8063,
     "leverage": "20x cross",
     "liqPx": 35.7529365335,
     "uPnl": 211829.689382,
     "entryTime": null,
     "entrySince": null
    }
   ],
   "rankPnl": 15,
   "rankRoi": 13,
   "changes": {
    "h1": {},
    "h4": {}
   }
  },
  {
   "addr": "0xcf5343ba750a6e30afbb1dadda08bc78f8c8ee11",
   "name": null,
   "accountValue": 13655737.113096,
   "monthPnl": 3690126.187973,
   "monthRoi": 0.701348146,
   "positions": [
    {
     "coin": "BTC",
     "side": "short",
     "szi": 1.0,
     "entryPx": 70073.0,
     "notionalUsd": 59283.0,
     "leverage": "5x cross",
     "liqPx": 10890317.34061037,
     "uPnl": 10790.086196,
     "entryTime": null,
     "entrySince": null
    },
    {
     "coin": "ETH",
     "side": "short",
     "szi": 4677.6279,
     "entryPx": 1923.29,
     "notionalUsd": 7474381.62141,
     "leverage": "4x cross",
     "liqPx": 3896.3714928315,
     "uPnl": 1522071.721531,
     "entryTime": null,
     "entrySince": null
    },
    {
     "coin": "SOL",
     "side": "short",
     "szi": 2271.62,
     "entryPx": 75.1012,
     "notionalUsd": 171670.86664,
     "leverage": "3x cross",
     "liqPx": 4785.4039947741,
     "uPnl": -1069.43996,
     "entryTime": null,
     "entrySince": null
    }
   ],
   "rankPnl": 16,
   "rankRoi": 6,
   "changes": {
    "h1": {},
    "h4": {}
   }
  },
  {
   "addr": "0x60a8c761f39696b3b419f31dcda20b405cb685f6",
   "name": null,
   "accountValue": 32296716.636116,
   "monthPnl": 3353364.648633,
   "monthRoi": 0.225845483,
   "positions": [
    {
     "coin": "BTC",
     "side": "long",
     "szi": 0.021,
     "entryPx": 66618.6,
     "notionalUsd": 1244.943,
     "leverage": "20x cross",
     "liqPx": null,
     "uPnl": -154.048,
     "entryTime": null,
     "entrySince": null
    }
   ],
   "rankPnl": 17,
   "rankRoi": 22,
   "changes": {
    "h1": {},
    "h4": {}
   }
  },
  {
   "addr": "0x4e23288cee4960f9f962195c22948e4bc7ae20c3",
   "name": null,
   "accountValue": 22062836.113989,
   "monthPnl": 3177676.775488,
   "monthRoi": 0.1907453398,
   "positions": [
    {
     "coin": "BTC",
     "side": "long",
     "szi": 0.008,
     "entryPx": 61129.3,
     "notionalUsd": 474.264,
     "leverage": "9x cross",
     "liqPx": null,
     "uPnl": -14.770405,
     "entryTime": null,
     "entrySince": null
    },
    {
     "coin": "SOL",
     "side": "long",
     "szi": 12.71,
     "entryPx": 82.02,
     "notionalUsd": 960.52012,
     "leverage": "20x cross",
     "liqPx": null,
     "uPnl": -81.954226,
     "entryTime": null,
     "entrySince": null
    }
   ],
   "rankPnl": 18,
   "rankRoi": 23,
   "changes": {
    "h1": {},
    "h4": {}
   }
  },
  {
   "addr": "0x856c35038594767646266bc7fd68dc26480e910d",
   "name": null,
   "accountValue": 62304975.066259995,
   "monthPnl": 3122987.426312,
   "monthRoi": 0.0651697178,
   "positions": [
    {
     "coin": "BTC",
     "side": "long",
     "szi": 9.34087,
     "entryPx": 60570.1,
     "notionalUsd": 553754.79621,
     "leverage": "20x cross",
     "liqPx": null,
     "uPnl": -12023.51382,
     "entryTime": null,
     "entrySince": null
    },
    {
     "coin": "ETH",
     "side": "long",
     "szi": 34.9875,
     "entryPx": 1648.68,
     "notionalUsd": 55906.52625,
     "leverage": "20x cross",
     "liqPx": null,
     "uPnl": -1776.92394,
     "entryTime": null,
     "entrySince": null
    },
    {
     "coin": "SOL",
     "side": "long",
     "szi": 827.66,
     "entryPx": 80.9431,
     "notionalUsd": 62547.92152,
     "leverage": "20x cross",
     "liqPx": null,
     "uPnl": -4445.47397,
     "entryTime": null,
     "entrySince": null
    },
    {
     "coin": "BNB",
     "side": "short",
     "szi": 74.038,
     "entryPx": 584.951,
     "notionalUsd": 40778.64964,
     "leverage": "5x cross",
     "liqPx": 64345.4129791704,
     "uPnl": 2529.98843,
     "entryTime": null,
     "entrySince": null
    },
    {
     "coin": "DOGE",
     "side": "short",
     "szi": 85.0,
     "entryPx": 0.090679,
     "notionalUsd": 6.16148,
     "leverage": "10x cross",
     "liqPx": 56555.6878677759,
     "uPnl": 1.546235,
     "entryTime": null,
     "entrySince": null
    },
    {
     "coin": "XRP",
     "side": "long",
     "szi": 450.0,
     "entryPx": 1.4633,
     "notionalUsd": 472.995,
     "leverage": "10x cross",
     "liqPx": null,
     "uPnl": -185.49,
     "entryTime": null,
     "entrySince": null
    },
    {
     "coin": "TAO",
     "side": "long",
     "szi": 147.359,
     "entryPx": 244.396,
     "notionalUsd": 30036.18497,
     "leverage": "5x cross",
     "liqPx": null,
     "uPnl": -5977.90043,
     "entryTime": null,
     "entrySince": 1781599288679
    }
   ],
   "rankPnl": 19,
   "rankRoi": 29,
   "changes": {
    "h1": {},
    "h4": {}
   }
  },
  {
   "addr": "0xaeaab54bbf65bfd6efed7d2eb68372298e3c2416",
   "name": null,
   "accountValue": 10481877.486038,
   "monthPnl": 3033491.856038,
   "monthRoi": 0.4072683675,
   "positions": [
    {
     "coin": "BTC",
     "side": "short",
     "szi": 1100.01,
     "entryPx": 58411.4,
     "notionalUsd": 65211892.83,
     "leverage": "20x cross",
     "liqPx": 67915.6449911079,
     "uPnl": -958724.616466,
     "entryTime": 1782831768844,
     "entrySince": null
    }
   ],
   "rankPnl": 20,
   "rankRoi": 15,
   "changes": {
    "h1": {},
    "h4": {
     "BTC": {
      "openedSz": 0.0,
      "closedSz": 100.0,
      "n": 2,
      "lastTime": 1782870240646
     }
    }
   }
  },
  {
   "addr": "0x13d032655aca891fad353e19424d2a087eccfa8a",
   "name": null,
   "accountValue": 17920389.308338,
   "monthPnl": 2386.418498,
   "monthRoi": 1.448354446,
   "positions": [
    {
     "coin": "XRP",
     "side": "short",
     "szi": 14605.0,
     "entryPx": 1.135968,
     "notionalUsd": 15351.3155,
     "leverage": "20x cross",
     "liqPx": 12.7616418877,
     "uPnl": 1239.504442,
     "entryTime": 1778851907490,
     "entrySince": null
    }
   ],
   "rankPnl": 33,
   "rankRoi": 1,
   "changes": {
    "h1": {},
    "h4": {}
   }
  },
  {
   "addr": "0xaf0fdd39e5d92499b0ed9f68693da99c0ec1e92e",
   "name": null,
   "accountValue": 13193152.561848,
   "monthPnl": 2166736.998944,
   "monthRoi": 0.7112679172,
   "positions": [
    {
     "coin": "BTC",
     "side": "long",
     "szi": 2.17551,
     "entryPx": 57835.0,
     "notionalUsd": 128970.75933,
     "leverage": "30x cross",
     "liqPx": null,
     "uPnl": 3150.13848,
     "entryTime": 1760129579273,
     "entrySince": null
    },
    {
     "coin": "ETH",
     "side": "short",
     "szi": 3539.5009,
     "entryPx": 1662.65,
     "notionalUsd": 5655768.48811,
     "leverage": "20x cross",
     "liqPx": 2919.4954638088,
     "uPnl": 229185.912573,
     "entryTime": 1760130763106,
     "entrySince": null
    },
    {
     "coin": "SOL",
     "side": "long",
     "szi": 97440.67,
     "entryPx": 71.0917,
     "notionalUsd": 7363786.31324,
     "leverage": "20x cross",
     "liqPx": 25.3497852238,
     "uPnl": 436556.565269,
     "entryTime": 1759308292903,
     "entrySince": null
    }
   ],
   "rankPnl": 23,
   "rankRoi": 5,
   "changes": {
    "h1": {},
    "h4": {}
   }
  },
  {
   "addr": "0xa98143608a6846453c88f29506d64a8b85532e65",
   "name": null,
   "accountValue": 15658483.425032,
   "monthPnl": 1900158.321151,
   "monthRoi": 0.6011320244,
   "positions": [
    {
     "coin": "ETH",
     "side": "short",
     "szi": 739.0,
     "entryPx": 2046.49,
     "notionalUsd": 1180848.1,
     "leverage": "20x cross",
     "liqPx": 10282.9849609249,
     "uPnl": 331512.044385,
     "entryTime": null,
     "entrySince": 1776581755220
    },
    {
     "coin": "SOL",
     "side": "short",
     "szi": 310.1,
     "entryPx": 89.515,
     "notionalUsd": 23434.8772,
     "leverage": "20x cross",
     "liqPx": 20672.0541476817,
     "uPnl": 4323.7243,
     "entryTime": 1773997784790,
     "entrySince": null
    }
   ],
   "rankPnl": 24,
   "rankRoi": 9,
   "changes": {
    "h1": {},
    "h4": {}
   }
  },
  {
   "addr": "0xa87a233e8a7d8951ff790a2e39738086cb5f71b7",
   "name": null,
   "accountValue": 21775409.065215,
   "monthPnl": 1492881.421772,
   "monthRoi": 0.3524627124,
   "positions": [
    {
     "coin": "SOL",
     "side": "short",
     "szi": 35362.23,
     "entryPx": 157.4282,
     "notionalUsd": 2672394.44556,
     "leverage": "20x cross",
     "liqPx": 356.8215233119,
     "uPnl": 2894617.921911,
     "entryTime": null,
     "entrySince": null
    },
    {
     "coin": "DOGE",
     "side": "short",
     "szi": 6754809.0,
     "entryPx": 0.182291,
     "notionalUsd": 489642.594792,
     "leverage": "10x cross",
     "liqPx": 1.5448627675,
     "uPnl": 741702.378394,
     "entryTime": null,
     "entrySince": null
    }
   ],
   "rankPnl": 25,
   "rankRoi": 16,
   "changes": {
    "h1": {},
    "h4": {}
   }
  },
  {
   "addr": "0xa445a0a15b1d50fa0c4bfe6796d9447e0da5329d",
   "name": null,
   "accountValue": 14412440.826101,
   "monthPnl": 2292808.778448,
   "monthRoi": 0.3515356494,
   "positions": [
    {
     "coin": "BTC",
     "side": "long",
     "szi": 69.07859,
     "entryPx": 59518.3,
     "notionalUsd": 4095186.05097,
     "leverage": "40x cross",
     "liqPx": 9784.2387459108,
     "uPnl": -16259.92589,
     "entryTime": null,
     "entrySince": 1778692743123
    }
   ],
   "rankPnl": 22,
   "rankRoi": 18,
   "changes": {
    "h1": {},
    "h4": {}
   }
  },
  {
   "addr": "0x9321d8117e73b0c79035f0e87debcfd8dbb1d75a",
   "name": null,
   "accountValue": 11932648.788741,
   "monthPnl": 1211326.115221,
   "monthRoi": 0.2768577924,
   "positions": [
    {
     "coin": "BTC",
     "side": "short",
     "szi": 36.83463,
     "entryPx": 62526.7,
     "notionalUsd": 2183667.37029,
     "leverage": "40x cross",
     "liqPx": 274270.2188864992,
     "uPnl": 119483.028566,
     "entryTime": null,
     "entrySince": 1752549287842
    },
    {
     "coin": "ETH",
     "side": "short",
     "szi": 1410.2636,
     "entryPx": 1638.63,
     "notionalUsd": 2253460.20644,
     "leverage": "25x cross",
     "liqPx": 7171.8557537629,
     "uPnl": 57444.050874,
     "entryTime": 1752868308818,
     "entrySince": null
    },
    {
     "coin": "SOL",
     "side": "short",
     "szi": 61996.05,
     "entryPx": 68.0676,
     "notionalUsd": 4685165.4906,
     "leverage": "20x cross",
     "liqPx": 201.7478095988,
     "uPnl": -465238.550083,
     "entryTime": null,
     "entrySince": null
    },
    {
     "coin": "XRP",
     "side": "short",
     "szi": 2017275.0,
     "entryPx": 1.163734,
     "notionalUsd": 2120357.7525,
     "leverage": "20x cross",
     "liqPx": 4.9288072044,
     "uPnl": 227214.914891,
     "entryTime": null,
     "entrySince": 1752553516210
    }
   ],
   "rankPnl": 27,
   "rankRoi": 20,
   "changes": {
    "h1": {},
    "h4": {}
   }
  }
 ],
 "aggregates": [
  {
   "coin": "BTC",
   "long": 12,
   "short": 8,
   "longNotional": 53096050.049490005,
   "shortNotional": 167576548.46940002,
   "totalNotional": 220672598.51889002,
   "score": -52
  },
  {
   "coin": "ETH",
   "long": 3,
   "short": 12,
   "longNotional": 58050.74826,
   "shortNotional": 159646224.79296002,
   "totalNotional": 159704275.54122,
   "score": -100
  },
  {
   "coin": "SOL",
   "long": 3,
   "short": 14,
   "longNotional": 7427294.75488,
   "shortNotional": 37847626.69884,
   "totalNotional": 45274921.45372,
   "score": -67
  },
  {
   "coin": "XRP",
   "long": 4,
   "short": 6,
   "longNotional": 2664502.7626,
   "shortNotional": 5915928.2031,
   "totalNotional": 8580430.9657,
   "score": -38
  },
  {
   "coin": "DOGE",
   "long": 0,
   "short": 6,
   "longNotional": 0.0,
   "shortNotional": 4490787.739151999,
   "totalNotional": 4490787.739151999,
   "score": -100
  },
  {
   "coin": "AVAX",
   "long": 1,
   "short": 4,
   "longNotional": 163870.576746,
   "shortNotional": 3123067.6748039997,
   "totalNotional": 3286938.2515499997,
   "score": -90
  },
  {
   "coin": "BNB",
   "long": 0,
   "short": 4,
   "longNotional": 0.0,
   "shortNotional": 1433680.34,
   "totalNotional": 1433680.34,
   "score": -100
  },
  {
   "coin": "TAO",
   "long": 1,
   "short": 4,
   "longNotional": 30036.18497,
   "shortNotional": 1148594.89129,
   "totalNotional": 1178631.07626,
   "score": -95
  },
  {
   "coin": "ATOM",
   "long": 1,
   "short": 1,
   "longNotional": 116916.402435,
   "shortNotional": 37625.7,
   "totalNotional": 154542.102435,
   "score": 51
  }
 ]
}