{
 "generatedAt": "2026-06-15T13:26:31+00:00",
 "generatedAtMs": 1781529981190,
 "window": "month",
 "topN": 20,
 "minAccount": 10000000,
 "focus": [
  "BTC",
  "ETH",
  "ATOM",
  "TAO",
  "XRP",
  "SOL",
  "BNB",
  "DOGE",
  "AVAX"
 ],
 "traders": [
  {
   "addr": "0x0ddf9bae2af4b874b96d287a5ad42eb47138a902",
   "name": "Penision Fund",
   "accountValue": 39639954.028726,
   "monthPnl": 21443902.616853,
   "monthRoi": 0.8185929352,
   "positions": [
    {
     "coin": "ETH",
     "side": "short",
     "szi": 60000.0,
     "entryPx": 1810.16,
     "notionalUsd": 109500000.0,
     "leverage": "3x cross",
     "liqPx": 2381.3105306737,
     "uPnl": -890213.978117,
     "entryTime": null,
     "entrySince": 1775071707334
    }
   ],
   "rankPnl": 1,
   "rankRoi": 3,
   "changes": {
    "h1": {},
    "h4": {}
   }
  },
  {
   "addr": "0xa9b95f2a2e7ef219021efc5c04c32761b8553bbd",
   "name": null,
   "accountValue": 32694463.770441,
   "monthPnl": 20324816.221196,
   "monthRoi": 2.8072238131,
   "positions": [
    {
     "coin": "BTC",
     "side": "short",
     "szi": 100.0,
     "entryPx": 72401.0,
     "notionalUsd": 6690800.0,
     "leverage": "20x cross",
     "liqPx": 181221.9543554766,
     "uPnl": 549307.815336,
     "entryTime": 1775640401701,
     "entrySince": null
    },
    {
     "coin": "ETH",
     "side": "short",
     "szi": 3000.0,
     "entryPx": 2314.09,
     "notionalUsd": 5475000.0,
     "leverage": "20x cross",
     "liqPx": 5607.447019115,
     "uPnl": 1467278.61679,
     "entryTime": 1775641030873,
     "entrySince": null
    }
   ],
   "rankPnl": 2,
   "rankRoi": 1,
   "changes": {
    "h1": {},
    "h4": {}
   }
  },
  {
   "addr": "0xecb63caa47c7c4e77f60f1ce858cf28dc2b82b00",
   "name": null,
   "accountValue": 103361621.954338,
   "monthPnl": 13809104.546799,
   "monthRoi": 0.087045895,
   "positions": [
    {
     "coin": "BTC",
     "side": "short",
     "szi": 264.574,
     "entryPx": 66109.7,
     "notionalUsd": 17698148.582,
     "leverage": "20x cross",
     "liqPx": 228262.2515652658,
     "uPnl": -207228.372019,
     "entryTime": null,
     "entrySince": 1781523798872
    },
    {
     "coin": "ETH",
     "side": "short",
     "szi": 24905.7207,
     "entryPx": 1714.88,
     "notionalUsd": 45423053.41266,
     "leverage": "15x cross",
     "liqPx": 3525.4243619984,
     "uPnl": -2712486.631801,
     "entryTime": null,
     "entrySince": 1781523604451
    },
    {
     "coin": "ATOM",
     "side": "long",
     "szi": 63029.54,
     "entryPx": 1.9253,
     "notionalUsd": 127193.61172,
     "leverage": "5x cross",
     "liqPx": null,
     "uPnl": 5836.768347,
     "entryTime": null,
     "entrySince": null
    },
    {
     "coin": "SOL",
     "side": "short",
     "szi": 193040.45,
     "entryPx": 67.2945,
     "notionalUsd": 14271094.3876,
     "leverage": "20x cross",
     "liqPx": 292.3974891953,
     "uPnl": -1280533.090713,
     "entryTime": null,
     "entrySince": 1781523628086
    },
    {
     "coin": "AVAX",
     "side": "long",
     "szi": 103328.27,
     "entryPx": 6.5121,
     "notionalUsd": 722378.268397,
     "leverage": "10x cross",
     "liqPx": null,
     "uPnl": 49490.579511,
     "entryTime": null,
     "entrySince": 1781523913813
    },
    {
     "coin": "BNB",
     "side": "short",
     "szi": 494.398,
     "entryPx": 603.485,
     "notionalUsd": 312128.28934,
     "leverage": "5x cross",
     "liqPx": 80364.9901165035,
     "uPnl": -13766.423546,
     "entryTime": null,
     "entrySince": 1781523629859
    },
    {
     "coin": "DOGE",
     "side": "short",
     "szi": 47908713.0,
     "entryPx": 0.087787,
     "notionalUsd": 4352171.215059,
     "leverage": "10x cross",
     "liqPx": 0.9259572944,
     "uPnl": -146388.493618,
     "entryTime": null,
     "entrySince": 1781523784694
    },
    {
     "coin": "XRP",
     "side": "short",
     "szi": 4099190.0,
     "entryPx": 1.157274,
     "notionalUsd": 5097342.765,
     "leverage": "10x cross",
     "liqPx": 11.4895082181,
     "uPnl": -353456.426353,
     "entryTime": null,
     "entrySince": 1781523706476
    },
    {
     "coin": "TAO",
     "side": "short",
     "szi": 3402.095,
     "entryPx": 270.158,
     "notionalUsd": 948163.8765,
     "leverage": "5x cross",
     "liqPx": 11829.813683607,
     "uPnl": -29057.442114,
     "entryTime": null,
     "entrySince": 1781523591020
    }
   ],
   "rankPnl": 3,
   "rankRoi": 7,
   "changes": {
    "h1": {},
    "h4": {
     "TAO": {
      "openedSz": 82.118,
      "closedSz": 6.308,
      "n": 79,
      "lastTime": 1781524613041
     },
     "ETH": {
      "openedSz": 191.45340000000002,
      "closedSz": 102.39040000000001,
      "n": 27,
      "lastTime": 1781524538034
     },
     "SOL": {
      "openedSz": 482.97,
      "closedSz": 330.66999999999996,
      "n": 22,
      "lastTime": 1781524510254
     },
     "BNB": {
      "openedSz": 0.0,
      "closedSz": 80.373,
      "n": 27,
      "lastTime": 1781524567014
     },
     "XRP": {
      "openedSz": 52918.0,
      "closedSz": 1717.0,
      "n": 35,
      "lastTime": 1781524619330
     },
     "DOGE": {
      "openedSz": 48015.0,
      "closedSz": 0.0,
      "n": 15,
      "lastTime": 1781524611322
     },
     "BTC": {
      "openedSz": 1.13773,
      "closedSz": 1.13398,
      "n": 3,
      "lastTime": 1781524289017
     },
     "AVAX": {
      "openedSz": 0.0,
      "closedSz": 277.52000000000004,
      "n": 3,
      "lastTime": 1781524504909
     }
    }
   }
  },
  {
   "addr": "0x7fdafde5cfb5465924316eced2d3715494c517d1",
   "name": "BobbyBigSize",
   "accountValue": 45771285.695815995,
   "monthPnl": 12676580.542189,
   "monthRoi": 0.3540510368,
   "positions": [
    {
     "coin": "BTC",
     "side": "short",
     "szi": 886.68847,
     "entryPx": 63208.3,
     "notionalUsd": 59313251.82371,
     "leverage": "20x cross",
     "liqPx": 102714.7323114729,
     "uPnl": -3267132.483972,
     "entryTime": null,
     "entrySince": 1781482903928
    },
    {
     "coin": "ETH",
     "side": "short",
     "szi": 35519.815,
     "entryPx": 1749.62,
     "notionalUsd": 64781038.597,
     "leverage": "15x cross",
     "liqPx": 2711.4501081491,
     "uPnl": -2634547.810713,
     "entryTime": null,
     "entrySince": 1781486741426
    },
    {
     "coin": "SOL",
     "side": "short",
     "szi": 2769.25,
     "entryPx": 72.6735,
     "notionalUsd": 204725.114,
     "leverage": "20x cross",
     "liqPx": 11403.8428897707,
     "uPnl": -3473.839388,
     "entryTime": null,
     "entrySince": null
    },
    {
     "coin": "AVAX",
     "side": "short",
     "szi": 734601.6,
     "entryPx": 13.2086,
     "notionalUsd": 5135673.24576,
     "leverage": "10x cross",
     "liqPx": 47.7094818678,
     "uPnl": 4567409.557483,
     "entryTime": null,
     "entrySince": null
    },
    {
     "coin": "BNB",
     "side": "short",
     "szi": 3333.132,
     "entryPx": 763.004,
     "notionalUsd": 2104306.22556,
     "leverage": "10x cross",
     "liqPx": 9414.9157106038,
     "uPnl": 438890.042718,
     "entryTime": null,
     "entrySince": null
    },
    {
     "coin": "DOGE",
     "side": "short",
     "szi": 40173473.0,
     "entryPx": 0.107293,
     "notionalUsd": 3649478.807739,
     "leverage": "10x cross",
     "liqPx": 0.8370902254,
     "uPnl": 660858.496851,
     "entryTime": null,
     "entrySince": 1781488546176
    },
    {
     "coin": "XRP",
     "side": "long",
     "szi": 3501550.0,
     "entryPx": 1.175889,
     "notionalUsd": 4354177.425,
     "leverage": "20x cross",
     "liqPx": null,
     "uPnl": 236742.57709,
     "entryTime": null,
     "entrySince": null
    },
    {
     "coin": "TAO",
     "side": "short",
     "szi": 3048.472,
     "entryPx": 259.298,
     "notionalUsd": 849609.1464,
     "leverage": "5x cross",
     "liqPx": 9869.1234165092,
     "uPnl": -59144.968946,
     "entryTime": null,
     "entrySince": null
    }
   ],
   "rankPnl": 4,
   "rankRoi": 5,
   "changes": {
    "h1": {},
    "h4": {}
   }
  },
  {
   "addr": "0x17c3c8fdbcb7d1b240ce08965e09b1fc91cba868",
   "name": null,
   "accountValue": 33324280.071588,
   "monthPnl": 11706501.507792,
   "monthRoi": 0.3196910017,
   "positions": [
    {
     "coin": "BTC",
     "side": "long",
     "szi": 32.49478,
     "entryPx": 75547.5,
     "notionalUsd": 2173673.31854,
     "leverage": "3x cross",
     "liqPx": null,
     "uPnl": -281228.222606,
     "entryTime": null,
     "entrySince": null
    },
    {
     "coin": "ETH",
     "side": "long",
     "szi": 0.5692,
     "entryPx": 2065.41,
     "notionalUsd": 1038.10696,
     "leverage": "20x cross",
     "liqPx": null,
     "uPnl": -137.529932,
     "entryTime": null,
     "entrySince": null
    },
    {
     "coin": "XRP",
     "side": "short",
     "szi": 68656.0,
     "entryPx": 2.199356,
     "notionalUsd": 85373.736,
     "leverage": "3x cross",
     "liqPx": 274.6328529023,
     "uPnl": 65625.2646,
     "entryTime": null,
     "entrySince": null
    }
   ],
   "rankPnl": 5,
   "rankRoi": 6,
   "changes": {
    "h1": {},
    "h4": {}
   }
  },
  {
   "addr": "0x77eeda199553e33b246e4b4666849b9ad0972902",
   "name": null,
   "accountValue": 11087963.87465,
   "monthPnl": 5297394.819884,
   "monthRoi": 0.9148314733,
   "positions": [
    {
     "coin": "ETH",
     "side": "short",
     "szi": 7062.0047,
     "entryPx": 1671.14,
     "notionalUsd": 12879684.17186,
     "leverage": "25x cross",
     "liqPx": 3186.5782458464,
     "uPnl": -1078022.38893,
     "entryTime": 1762290876198,
     "entrySince": null
    },
    {
     "coin": "SOL",
     "side": "short",
     "szi": 4746.19,
     "entryPx": 66.6471,
     "notionalUsd": 350876.33432,
     "leverage": "20x cross",
     "liqPx": 2091.7571002544,
     "uPnl": -34556.08226,
     "entryTime": 1761573133363,
     "entrySince": null
    },
    {
     "coin": "DOGE",
     "side": "short",
     "szi": 3514547.0,
     "entryPx": 0.084512,
     "notionalUsd": 319271.993121,
     "leverage": "10x cross",
     "liqPx": 2.7509230845,
     "uPnl": -22247.746076,
     "entryTime": 1761573133479,
     "entrySince": null
    },
    {
     "coin": "XRP",
     "side": "short",
     "szi": 1012803.0,
     "entryPx": 1.310932,
     "notionalUsd": 1259420.5305,
     "leverage": "20x cross",
     "liqPx": 10.6994359494,
     "uPnl": 68296.120506,
     "entryTime": 1761685641537,
     "entrySince": null
    }
   ],
   "rankPnl": 6,
   "rankRoi": 2,
   "changes": {
    "h1": {},
    "h4": {}
   }
  },
  {
   "addr": "0xb798aef79972ce8f73d47b9ebbcda6bbb7ec4fbf",
   "name": null,
   "accountValue": 13334500.171244,
   "monthPnl": 4869207.162979,
   "monthRoi": 0.5751897829,
   "positions": [
    {
     "coin": "BTC",
     "side": "short",
     "szi": 380.0,
     "entryPx": 67246.1,
     "notionalUsd": 25419340.0,
     "leverage": "2x isolated",
     "liqPx": 100003.9678262924,
     "uPnl": 134207.480597,
     "entryTime": 1774616698700,
     "entrySince": null
    },
    {
     "coin": "ETH",
     "side": "short",
     "szi": 87.9114,
     "entryPx": 1985.82,
     "notionalUsd": 160332.81132,
     "leverage": "2x isolated",
     "liqPx": 2924.6647683874,
     "uPnl": 14243.73954,
     "entryTime": 1779970426756,
     "entrySince": null
    },
    {
     "coin": "SOL",
     "side": "short",
     "szi": 1391.61,
     "entryPx": 80.7543,
     "notionalUsd": 102878.94408,
     "leverage": "2x cross",
     "liqPx": 118.5314304649,
     "uPnl": 9499.61774,
     "entryTime": 1779970453131,
     "entrySince": null
    }
   ],
   "rankPnl": 7,
   "rankRoi": 4,
   "changes": {
    "h1": {},
    "h4": {}
   }
  }
 ],
 "aggregates": [
  {
   "coin": "ETH",
   "long": 1,
   "short": 6,
   "longNotional": 1038.10696,
   "shortNotional": 238219108.99284002,
   "totalNotional": 238220147.09980002,
   "score": -100
  },
  {
   "coin": "BTC",
   "long": 1,
   "short": 4,
   "longNotional": 2173673.31854,
   "shortNotional": 109121540.40571,
   "totalNotional": 111295213.72425,
   "score": -96
  },
  {
   "coin": "SOL",
   "long": 0,
   "short": 4,
   "longNotional": 0.0,
   "shortNotional": 14929574.78,
   "totalNotional": 14929574.78,
   "score": -100
  },
  {
   "coin": "XRP",
   "long": 1,
   "short": 3,
   "longNotional": 4354177.425,
   "shortNotional": 6442137.0315,
   "totalNotional": 10796314.4565,
   "score": -19
  },
  {
   "coin": "DOGE",
   "long": 0,
   "short": 3,
   "longNotional": 0.0,
   "shortNotional": 8320922.015919,
   "totalNotional": 8320922.015919,
   "score": -100
  },
  {
   "coin": "AVAX",
   "long": 1,
   "short": 1,
   "longNotional": 722378.268397,
   "shortNotional": 5135673.24576,
   "totalNotional": 5858051.514157,
   "score": -75
  },
  {
   "coin": "BNB",
   "long": 0,
   "short": 2,
   "longNotional": 0.0,
   "shortNotional": 2416434.5149000003,
   "totalNotional": 2416434.5149000003,
   "score": -100
  },
  {
   "coin": "TAO",
   "long": 0,
   "short": 2,
   "longNotional": 0.0,
   "shortNotional": 1797773.0229,
   "totalNotional": 1797773.0229,
   "score": -100
  },
  {
   "coin": "ATOM",
   "long": 1,
   "short": 0,
   "longNotional": 127193.61172,
   "shortNotional": 0.0,
   "totalNotional": 127193.61172,
   "score": 100
  }
 ]
}